Workbook

Sheet INVOICE
L2: Updated 01/25/2017
K7: INVOICE #: | M7: ='MATERIAL AND LABOR BREAKDOWN'!C7 -> 0
K8: INVOICE DATE: | M8: ='MATERIAL AND LABOR BREAKDOWN'!C6 -> 44167
K9: SR# | M9: ='MATERIAL AND LABOR BREAKDOWN'!C9 -> PROJECT FORUM
C13: CUSTOMER: | J13: LOCATION:
C14: ='MATERIAL AND LABOR BREAKDOWN'!C2 -> VIXXO | J14: STORE | K14: ='MATERIAL AND LABOR BREAKDOWN'!C3 -> SEI/Exxon #40059
J15: ADDRESS | K15: ='MATERIAL AND LABOR BREAKDOWN'!C4 -> 13825 Lee Hwy
J16: CITY,ST,ZIP | K16: ='MATERIAL AND LABOR BREAKDOWN'!C5 -> Centerville, VA 20121
C18: ATTN: | D18: ='MATERIAL AND LABOR BREAKDOWN'!C8 -> PAUL ENCINAS
B23: SCOPE OF WORK | F23: DESCRIPTION OF WORK:
B24: STP SUMPS, MOTORS, LD'S SENSORS, AND FIBERLITE MANOLES | F24: REMOVE AND REPLACE TANK TOP STP'S WITH 7-ELEVEN SPEC BRAVO FRP RETROFIT SUMPS, FE PETRO MOTORS, VAPORLESS LD'S, AND FIBERLITE FLUSHMOUNT MANHOLES. REPLACE 18" MANHOLES ON TANK TOP WITH 7-11 SPEC OPW WATERTIGHT MANHOLES DURING EXCAVATION.
B25: UDC'S, CUSTOM STAINLESS STEEL ISLANDS, AND BOLLARDS | F25: REMOVE AND REPLACE ALL EXISTING DISPENSER SUMPS ) WITH 7-ELEVEN SPEC OPW FRP UDC'S, 3'X9x13" STAINLESS STEEL ISLANDS, AND BOLLARDS ON OUTSIDE OF ISLANDS. * WILL NEED LONG ISLASNDS TO ENCOMPASS CANOPY WRAP/COLUMN.
B26: OPW FLEXWORKS PRODUCT LINES AND 10+1 SHEAR VALVES | F26: REMOVE AND REPLACE EXISTING PRODUCT LINES WITH OPW FLEXORKS DW PIPING USING 7-11 SPEC DPC COUPLINGS AND INSTALL OPW 10+1 SHEAR VALVES
B27: OPW DOUBLE WALL SPILL BUCKETS | F27: REMOVE AND REPLACE EXISTING SPILL BUCKETS WITH 7-11 SPEC OPW 3100 DW SHEAR VALVES. (3) FILL, (2) VAPOR
B28: WIRING AND SENSORS | F28: MAKE REPAIRS TO EXISTING CONDUITS USING ROB ROY AND JUNCTION MANWAY. PULL NEW DISPENSER WIRE, 7-11 CAT 6, STP WIRE, AND SENSOR WIRE. INSTALL SENSORS IN ALL SECONDARY CONTAINMENT AND UPGRADE TLS-350 ACCORDINGLY.
B29: TANKNOLOGY, MISC | F29: PURGE, CALIBRATE, START UP DISPENSERS. MEET TANKNOLOGY ONSITE TO ENSURE SMOOTH TRANSITION TO OPEN FUEL SALES.
B31: 9 - EQUIPMENT / REMOVAL & DISPOSAL / PERMIT FEE | I31: MATERIAL | J31: UNIT | K31: SERVICE RATE | L31: SERVICE TOTAL | M31: TOTAL MATERIAL & LABOR
B32: 1 | C32: ='MATERIAL AND LABOR BREAKDOWN'!C333 -> BOBCAT FOR REMOVING DISPENSERS | I32: 0 | L32: ='MATERIAL AND LABOR BREAKDOWN'!J333 -> 850 | M32: ='MATERIAL AND LABOR BREAKDOWN'!J333 -> 850
B33: 2 | C33: ='MATERIAL AND LABOR BREAKDOWN'!B334 -> BREAKER ATTACHMENT | I33: 0 | L33: ='MATERIAL AND LABOR BREAKDOWN'!J334 -> 225 | M33: =SUM(I33+L33) -> 225
B34: 3 | C34: ='MATERIAL AND LABOR BREAKDOWN'!C335 -> SUPER VAC TRUCK - EXCAVATION | I34: 0 | L34: ='MATERIAL AND LABOR BREAKDOWN'!J335 -> 2500 | M34: =SUM(I34+L34) -> 2500
B35: 4 | C35: ='MATERIAL AND LABOR BREAKDOWN'!C336 -> 16" CONCRETE SAW W/BLADE | I35: 0 | L35: ='MATERIAL AND LABOR BREAKDOWN'!J336 -> 90 | M35: =SUM(I35+L35) -> 90
B36: 5 | C36: ='MATERIAL AND LABOR BREAKDOWN'!B337 -> P185 AIR COMPRESSOR | I36: 0 | L36: ='MATERIAL AND LABOR BREAKDOWN'!J337 -> 250 | M36: ='MATERIAL AND LABOR BREAKDOWN'!J337 -> 250
B37: 6 | C37: ='MATERIAL AND LABOR BREAKDOWN'!C338 -> MINI EXCAVATOR | I37: 0 | L37: ='MATERIAL AND LABOR BREAKDOWN'!J338 -> 1150 | M37: =SUM(I37+L37) -> 1150
B38: 7 | C38: ='MATERIAL AND LABOR BREAKDOWN'!C339 -> WATER TRAILER FOR HYDRO TESTING | I38: 0 | L38: ='MATERIAL AND LABOR BREAKDOWN'!J339 -> 225 | M38: =SUM(I38+L38) -> 225
B39: 8 | C39: ='MATERIAL AND LABOR BREAKDOWN'!C340 -> CONFINED SPACE BLOWER/HEATER | I39: 0 | L39: ='MATERIAL AND LABOR BREAKDOWN'!J340 -> 175 | M39: =SUM(I39+L39) -> 175
B40: 7 | C40: ='MATERIAL AND LABOR BREAKDOWN'!C341 -> SITE FENCING - BARRICADES | I40: 0 | L40: ='MATERIAL AND LABOR BREAKDOWN'!J341 -> 225 | M40: =SUM(I40+L40) -> 225
B41: 8 | C41: ='MATERIAL AND LABOR BREAKDOWN'!C343 -> PERMIT FEE - ELECTRICAL / MECHANICAL | I41: 0 | L41: ='MATERIAL AND LABOR BREAKDOWN'!J342 -> 0 | M41: ='MATERIAL AND LABOR BREAKDOWN'!J343 -> 2000
H42: Sub Total Material: | I42: =SUM(I32:I35) -> 0 | J42: ServiceTotal: | L42: =SUM(L32:L35) -> 3665
B43: (9)REMOVAL AND DISPOSAL TOTAL: | M43: =SUM(M32:N42) -> 7690
B44: ONSITE LABOR | I44: MATERIAL | J44: LABOR HOURS | K44: LABOR RATE | L44: TOTAL LABOR | M44: TOTAL MATERIAL & LABOR
B45: 1 | C45: ='MATERIAL AND LABOR BREAKDOWN'!C305 -> TOTAL ON-SITE LABOR | I45: 0 | J45: ='MATERIAL AND LABOR BREAKDOWN'!I294 -> 1556 | K45: ='MATERIAL AND LABOR BREAKDOWN'!D285 -> 70 | L45: =SUM(J45*K45) -> 108920 | M45: ='MATERIAL AND LABOR BREAKDOWN'!J294 -> 90720
B46: 2 | C46: SERVICE COMMISSION AND START UP | I46: 0 | J46: 20 | K46: 70 | L46: =SUM(J46*K46) -> 1400 | M46: =SUM(I46+L46) -> 1400
B47: 3 | I47: 0 | L47: =SUM(J47*K47) -> 0 | M47: =SUM(I47+L47) -> 0
B48: 4 | I48: 0 | L48: =SUM(J48*K48) -> 0 | M48: =SUM(I48+L48) -> 0
B49: 5 | I49: 0 | M49: 0
B50: 6 | I50: 0 | L50: =SUM(J50*K50) -> 0 | M50: ='MATERIAL AND LABOR BREAKDOWN'!J282 -> 0
B51: 7 | C51: ='MATERIAL AND LABOR BREAKDOWN'!C269 -> CONCRETE / REBAR / BACKFILL | I51: 0 | L51: =SUM(J51*K51) -> 0 | M51: ='MATERIAL AND LABOR BREAKDOWN'!J269 -> 11875
B52: 8 | C52: MISC / DISPOSABLES / BARRELS / RAGS / THREAD SEALANT / NITROGEN | I52: 0 | L52: =SUM(J52*K52) -> 0 | M52: ='MATERIAL AND LABOR BREAKDOWN'!J358 -> 585.18
H53: Sub Total Material: | I53: 0 | L53: =SUM(L45:L52) -> 110320
M54: =SUM(M45:N53) -> 104580.18
B55: PARTS, MATERIALS, AND SUPPLIES | I55: MATERIAL | J55: UNIT | K55: PRICE | L55: TOTAL | M55: TOTAL MATERIAL & LABOR
B56: 1 | C56: ='MATERIAL AND LABOR BREAKDOWN'!C114 -> TOTAL ELECTRICAL MATERIALS | I56: ='MATERIAL AND LABOR BREAKDOWN'!J114 -> 14166.656 | L56: =SUM(J56*K56) -> 0 | M56: ='MATERIAL AND LABOR BREAKDOWN'!J114 -> 14166.656
B57: 2 | C57: ='MATERIAL AND LABOR BREAKDOWN'!C155 -> TOTAL PIPING - FERGUSONS SUPPLY | I57: ='MATERIAL AND LABOR BREAKDOWN'!J155 -> 3502.712 | L57: =SUM(J57*K57) -> 0 | M57: ='MATERIAL AND LABOR BREAKDOWN'!J155 -> 3502.712
B58: 3 | C58: ='MATERIAL AND LABOR BREAKDOWN'!C192 -> TOTAL ICON MATERIALS | I58: ='MATERIAL AND LABOR BREAKDOWN'!J192 -> 0 | L58: =SUM(J58*K58) -> 0 | M58: ='MATERIAL AND LABOR BREAKDOWN'!J192 -> 0
B59: 4 | C59: ='MATERIAL AND LABOR BREAKDOWN'!C256 -> TOTAL SOURCE / PETRO MATERIALS | I59: ='MATERIAL AND LABOR BREAKDOWN'!J256 -> 425.772 | L59: =SUM(J59*K59) -> 0 | M59: ='MATERIAL AND LABOR BREAKDOWN'!J256 -> 425.772
B60: 5 | I60: 0 | L60: =SUM(J60*K60) -> 0 | M60: =SUM(I60+L60) -> 0
B61: 6 | I61: 0 | L61: =SUM(J61*K61) -> 0 | M61: =SUM(I61+L61) -> 0
B62: 7 | I62: 0 | L62: =SUM(J62*K62) -> 0 | M62: =SUM(I62+L62) -> 0
B63: 8 | I63: 0 | L63: =SUM(J63*K63) -> 0 | M63: 0
F64: PARTS, MATERIALS, AND SUPPLIES | I64: =SUM(I56:I63) -> 18095.14 | L64: =SUM(L56:L63) -> 0
B65: SUB-TOTAL AMOUNT | M65: =SUM(I64,M54,M43) -> 130365.32
B66: PROFIT AND OVERHEAD | L66: 0.04 | M66: =SUM(M65*L66) -> 5214.6128
B67: VA SALES TAX | L67: 0.053 | M67: =SUM(I64*L67) -> 959.04239
B68: GRAND TOTAL INVOICE: | M68: =SUM(M65:N67) -> 136538.97
C71: Fred W. Dodson III (Trae) | H71: ='MATERIAL AND LABOR BREAKDOWN'!C6 -> 44167
C72: Construction Manager | H72: DATE

Sheet MATERIAL AND LABOR BREAKDOWN
B2: CUSTOMER | C2: VIXXO
B3: SITE # | C3: SEI/Exxon #40059
B4: ADDRESS | C4: 13825 Lee Hwy
B5: CITY, STATE | C5: Centerville, VA 20121
B6: INVOICE DATE: | C6: 44167
B7: INVOICE NUMBER:
B8: PROJECT MANAGER | C8: PAUL ENCINAS
B9: SR# | C9: PROJECT FORUM
A11: 1 | B11: ELECTRICAL SUPPLY - EECO / CAPITAL TRISTATE/HOME DEPOT
B12: PART # | C12: DESCRIPTION | D12: CURRENT PRICING | H12: Freight | I12: Amount | J12: Sell Price
B13: 3/4 INCH GALV AND EXPLOSION PROOF
B14: BBDX1 | C14: 1LB DUCK SEAL | D14: 4.53 | F14: =D14*25% -> 1.1325 | G14: =F14+D14 -> 5.6625 | J14: =SUM(I14*G14) -> 0
B15: CBCHICOA19PX | C15: SEAL COMP | D15: 34.89 | F15: =D15*25% -> 8.7225 | G15: =F15+D15 -> 43.6125 | J15: =SUM(I15*G15) -> 0
B16: CBCHICOA3 | C16: 1LB SEAL COMP - CHICO | D16: 10.48 | F16: =D16*25% -> 2.62 | G16: =F16+D16 -> 13.1 | I16: 5 | J16: =SUM(I16*G16) -> 65.5
B17: CBEYS21 | C17: 3/4 FEM COND SEAL - SEAL OFF | D17: 34.64 | F17: =D17*25% -> 8.66 | G17: =F17+D17 -> 43.3 | I17: 32 | J17: =SUM(I17*G17) -> 1385.6
B18: CBGUP214 | C18: GUP214 JCT BOX - LARGE J-BOX | D18: 94.73 | F18: =D18*25% -> 23.6825 | G18: =F18+D18 -> 118.4125 | I18: 12 | J18: =SUM(I18*G18) -> 1420.95
B19: CBLBY25 | C19: 3/4 90D COND ELL - PULL 90 | D19: 26 | F19: =D19*25% -> 6.5 | G19: =F19+D19 -> 32.5 | I19: 28 | J19: =SUM(I19*G19) -> 910
B20: CBOELB2 | C20: 3/4 OELB COND BODY&CVR L-BOX | D20: 62.22 | F20: =D20*25% -> 15.555 | G20: =F20+D20 -> 77.775 | J20: =SUM(I20*G20) -> 0
B21: CBPLG2 | C21: 3/4 RECES PLUG | D21: 2.35 | F21: =D21*25% -> 0.5875 | G21: =F21+D21 -> 2.9375 | J21: =SUM(I21*G21) -> 0
B22: CBRE21 | C22: 3/4X1/2 REDUCER BUSHING | D22: 0.536 | F22: =D22*25% -> 0.134 | G22: =F22+D22 -> 0.67 | I22: 5 | J22: =SUM(I22*G22) -> 3.35
B23: CBRE32 | C23: 1X3/4 RED | D23: 2.35 | F23: =D23*25% -> 0.5875 | G23: =F23+D23 -> 2.9375 | I23: 13 | J23: =SUM(I23*G23) -> 38.1875
B24: CBUNF205 | C24: 3/4 FEM UNION | D24: 26.07 | F24: =D24*25% -> 6.5175 | G24: =F24+D24 -> 32.5875 | I24: 12 | J24: =SUM(I24*G24) -> 391.05
B25: CBUNY205 | C25: 3/4 MALE UNION | D25: 28.5 | F25: =D25*25% -> 7.125 | G25: =F25+D25 -> 35.625 | I25: 15 | J25: =SUM(I25*G25) -> 534.375
B26: CF3/4GACP | C26: 3/4XCL GALV COND NIPPLE | D26: 1.62 | F26: =D26*25% -> 0.405 | G26: =F26+D26 -> 2.025 | I26: 12 | J26: =SUM(I26*G26) -> 24.3
B27: CF3/4X2GANIP | C27: 3/4X2 GALV COND NIPPLE | D27: 1.96 | F27: =D27*25% -> 0.49 | G27: =F27+D27 -> 2.45 | I27: 12 | J27: =SUM(I27*G27) -> 29.4
B28: CF3/4X3GANIP | C28: 3/4X3 GALV COND NIPPLE | D28: 2.31 | F28: =D28*25% -> 0.5775 | G28: =F28+D28 -> 2.8875 | I28: 12 | J28: =SUM(I28*G28) -> 34.65
B29: CF3/4X4GANIP | C29: 3/4X4 GALV COND NIPPLE | D29: 2.68 | F29: =D29*25% -> 0.67 | G29: =F29+D29 -> 3.35 | I29: 12 | J29: =SUM(I29*G29) -> 40.2
B30: CF3/4X5GANIP | C30: 3/4X5 GALV COND NIPPLE | D30: 2.97 | F30: =D30*25% -> 0.7425 | G30: =F30+D30 -> 3.7125 | I30: 12 | J30: =SUM(I30*G30) -> 44.55
B31: CF3/4X6GANIP | C31: 3/4X6 GALV COND NIPPLE | D31: 3.32 | F31: =D31*25% -> 0.83 | G31: =F31+D31 -> 4.15 | I31: 12 | J31: =SUM(I31*G31) -> 49.8
B32: CF3/4X8GANIP | C32: 3/4X8GALV COND NIPPLE | D32: 4.85 | F32: =D32*25% -> 1.2125 | G32: =F32+D32 -> 6.0625 | I32: 12 | J32: =SUM(I32*G32) -> 72.75
B33: CF3/4X10GANIP | C33: 3/4X10 GALV COND NIPPLE | D33: 5.51 | F33: =D33*25% -> 1.3775 | G33: =F33+D33 -> 6.8875 | I33: 12 | J33: =SUM(I33*G33) -> 82.65
B34: CF3/4GACP | C34: 3/4" GALV COUPL | D34: 2.147 | F34: =D34*25% -> 0.53675 | G34: =F34+D34 -> 2.68375 | I34: 12 | J34: =SUM(I34*G34) -> 32.205
B35: CO3/4GA | C35: 3/4" GALVANIZED CONDUIT | D35: 13.36 | F35: =D35*25% -> 3.34 | G35: =F35+D35 -> 16.7 | J35: =SUM(I35*G35) -> 0
B36: PV3/4 | C36: 3/4" PVC CONDUIT SCH 40 | D36: 21.93 | F36: =D36*25% -> 5.4825 | G36: =F36+D36 -> 27.4125 | J36: =SUM(I36*G36) -> 0
B37: ID30071 | C37: SIZE 71B GRY WIRECONN | D37: 6.53 | F37: =D37*25% -> 1.6325 | G37: =F37+D37 -> 8.1625 | J37: =SUM(I37*G37) -> 0
B38: ID30072 | C38: SIZE 72B BLU WIRECONN | D38: 7.37 | F38: =D38*25% -> 1.8425 | G38: =F38+D38 -> 9.2125 | J38: =SUM(I38*G38) -> 0
B39: ID30073 | C39: SIZE 73B ORG WIRECONN | D39: 8.52 | F39: =D39*25% -> 2.13 | G39: =F39+D39 -> 10.65 | J39: =SUM(I39*G39) -> 0
B40: PV3/4 | C40: 3/4" PVC CONDUIT SCH 40 | D40: 21.93 | F40: =D40*25% -> 5.4825 | G40: =F40+D40 -> 27.4125 | J40: =SUM(I40*G40) -> 0
B41: PV3/4FTA | C41: 3/4" PVC FEMALE ADAPTER | D41: 0.23 | F41: =D41*25% -> 0.0575 | G41: =F41+D41 -> 0.2875 | J41: =SUM(I41*G41) -> 0
B42: THREADED CONDUIT BUSHING 3/4" | C42: THREADED CONDUIT BUSHING - 3/4 | D42: 0.55 | F42: =D42*25% -> 0.1375 | G42: =F42+D42 -> 0.6875 | I42: 32 | J42: =SUM(I42*G42) -> 22
B43: RIGID SWEEP 90 | C43: RIGID SWEEP 90 | D43: 5.91 | F43: =D43*25% -> 1.4775 | G43: =F43+D43 -> 7.3875 | J43: =SUM(I43*G43) -> 0
B44: PVC COATED CONDUIT | C44: ROB ROY | D44: 54 | F44: =D44*25% -> 13.5 | G44: =F44+D44 -> 67.5 | I44: 22 | J44: =SUM(I44*G44) -> 1485
B45: 3/4" FLEXIBLE CONNECTOR ELBOW | C45: 3/4 FLEX CONDUIT CONNECTOR ELBOW 90 | D45: 1.39 | F45: =D45*25% -> 0.3475 | G45: =F45+D45 -> 1.7375 | J45: =SUM(I45*G45) -> 0
B46: 3/4 INCH ALUMINUM FLEXIBLE COND | C46: FLEXIBLE CONDUIT - 3/4" ALUM -PER FT | D46: 0.9 | F46: =D46*25% -> 0.225 | G46: =F46+D46 -> 1.125 | J46: =SUM(I46*G46) -> 0
B47: EMT 3/4 AND 1 INCH
B48: 10 FOOT STICK 1" EMT | C48: EMT CONDUIT 10 FOOT - 1 INCH | D48: 14.2 | F48: =D48*25% -> 3.55 | G48: =F48+D48 -> 17.75 | J48: =SUM(I48*G48) -> 0
B49: 10 FOOT STICK 3/4" EMT | C49: 3/4 INCH 10FT STEEL EMT | D49: 8.2 | F49: =D49*25% -> 2.05 | G49: =F49+D49 -> 10.25 | J49: =SUM(I49*G49) -> 0
B50: 3/4" BOX CONNECTOR-COMPRESSION | C50: 3/4 EMT COMPRESSION J BOX CONNECTOR | D50: 1.31 | F50: =D50*25% -> 0.3275 | G50: =F50+D50 -> 1.6375 | J50: =SUM(I50*G50) -> 0
B51: 3/4" COMPRESSION COUPLING | C51: 3/4 EMT COMPRESSION COUPLING | D51: 1.5 | F51: =D51*25% -> 0.375 | G51: =F51+D51 -> 1.875 | J51: =SUM(I51*G51) -> 0
B52: 3/4" COMP COUPLING - RAIN TIGHT | C52: 3/4" RAIN TIGHT COMPRESSION COUPLING | D52: 1.35 | F52: =D52*25% -> 0.3375 | G52: =F52+D52 -> 1.6875 | J52: =SUM(I52*G52) -> 0
B53: EMT PULL 90 3/4" | C53: EMT PULL 90 - 3/4 - RAINT TIGHT | D53: 10.73 | F53: =D53*25% -> 2.6825 | G53: =F53+D53 -> 13.4125 | J53: =SUM(I53*G53) -> 0
B54: EMT 3/4 STRAP | C54: 3/4" STRAP | D54: 0.35 | F54: =D54*25% -> 0.0875 | G54: =F54+D54 -> 0.4375 | J54: =SUM(I54*G54) -> 0
B55: ORBOF7712 | C55: EMT STEEL SET SCREW COUPLING | D55: 0.21 | F55: =D55*25% -> 0.0525 | G55: =F55+D55 -> 0.2625 | J55: =SUM(I55*G55) -> 0
B56: SC500SC | C56: 1/4" BEAM CLAMP 20TPI | D56: 0.81 | F56: =D56*25% -> 0.2025 | G56: =F56+D56 -> 1.0125 | J56: =SUM(I56*G56) -> 0
B57: CF3/4EMTEL | C57: 3/4" EMT ELBOW 90DEG | D57: 2 | F57: =D57*25% -> 0.5 | G57: =F57+D57 -> 2.5 | J57: =SUM(I57*G57) -> 0
B58: SCBU502 | C58: 3/4" 105D PLASTIC BUSHING | D58: 0.1 | F58: =D58*25% -> 0.025 | G58: =F58+D58 -> 0.125 | J58: =SUM(I58*G58) -> 0
B59: 3/4" EMT SWEEP 90 | C59: 3/4" SWEEP 90 | D59: 4.57 | F59: =D59*25% -> 1.1425 | G59: =F59+D59 -> 5.7125 | J59: =SUM(I59*G59) -> 0
B60: 3PC UNION-DIRECT BURY EP | C60: EXPLOSION PROOF ERICKSON | D60: 33.15 | F60: =D60*25% -> 8.2875 | G60: =F60+D60 -> 41.4375 | I60: 28 | J60: =SUM(I60*G60) -> 1160.25
D61: 0 | F61: =D61*25% -> 0 | G61: =F61+D61 -> 0 | J61: =SUM(I61*G61) -> 0
D62: 0 | F62: =D62*25% -> 0 | G62: =F62+D62 -> 0 | J62: =SUM(I62*G62) -> 0
D63: 0 | F63: =D63*25% -> 0 | G63: =F63+D63 -> 0 | J63: =SUM(I63*G63) -> 0
B64: 1 INCH FLEXIBLE / GALVANIZED AND EXPLOSION PROOF
B65: EYS31 | C65: 1" EXPLOSION PROOF SEAL OFF | D65: 44.66 | F65: =D65*25% -> 11.165 | G65: =F65+D65 -> 55.825 | J65: =SUM(I65*G65) -> 0
B66: UNF305 | C66: 1" STEEL FEMALE CONDUIT UNION | D66: 49.68 | F66: =D66*25% -> 12.42 | G66: =F66+D66 -> 62.1 | J66: =SUM(I66*G66) -> 0
B67: 1" BOX CONNECT-FLEXIBLE | C67: 1" BOX CONNECTORS-FLEXIBLE | D67: 2.01 | F67: =D67*25% -> 0.5025 | G67: =F67+D67 -> 2.5125 | J67: =SUM(I67*G67) -> 0
B68: 1" FLEXIBLE CONDUIT | C68: FLEXIBLE CONDUIT - 1" - 50 FOOT | D68: 92.53 | F68: =D68*25% -> 23.1325 | G68: =F68+D68 -> 115.6625 | J68: =SUM(I68*G68) -> 0
B69: 1"X6" GALV NIPPLE | C69: 1"X6" GALV NIPPLE | D69: 3.47 | F69: =D69*25% -> 0.8675 | G69: =F69+D69 -> 4.3375 | J69: =SUM(I69*G69) -> 0
B70: 1"XCLOSE | C70: 1" X CLOSE GALVANIZED NIPPLE | D70: 2.13 | F70: =D70*25% -> 0.5325 | G70: =F70+D70 -> 2.6625 | J70: =SUM(I70*G70) -> 0
B71: 100GC | C71: 1 " GALV COUPLING | D71: 2.94 | F71: =D71*25% -> 0.735 | G71: =F71+D71 -> 3.675 | J71: =SUM(I71*G71) -> 0
B72: 1"X2" GALV NIPPLE | C72: 1" X 2" GALVANIZED NIPPLE | D72: 2.62 | F72: =D72*25% -> 0.655 | G72: =F72+D72 -> 3.275 | J72: =SUM(I72*G72) -> 0
B73: 1"x3" GALV NIPPLE | C73: 1"x3" GALV NIPPLE | D73: 3.25 | F73: =D73*25% -> 0.8125 | G73: =F73+D73 -> 4.0625 | J73: =SUM(I73*G73) -> 0
B74: RE32 | C74: 1" TO 3/4" REDUCING BUSHING | D74: 5.63 | F74: =D74*25% -> 1.4075 | G74: =F74+D74 -> 7.0375 | J74: =SUM(I74*G74) -> 0
B75: 1" CONDUIT STRAPS | C75: 1" CONDUIT STRAPS | D75: 0.65 | F75: =D75*25% -> 0.1625 | G75: =F75+D75 -> 0.8125 | J75: =SUM(I75*G75) -> 0
D76: 0 | F76: =D76*25% -> 0 | G76: =F76+D76 -> 0 | J76: =SUM(I76*G76) -> 0
D77: 0 | F77: =D77*25% -> 0 | G77: =F77+D77 -> 0 | J77: =SUM(I77*G77) -> 0
D78: 0 | F78: =D78*25% -> 0 | G78: =F78+D78 -> 0 | J78: =SUM(I78*G78) -> 0
B79: MISC ELECTRICAL SUPPLIES
B80: PULL STRING | C80: PULL STRING - CAPITAL ELECTRIC - 2200' | D80: 54.64 | F80: =D80*20% -> 10.928 | G80: =F80+D80 -> 65.568 | I80: 1 | J80: =SUM(I80*G80) -> 65.568
B81: SCXC272 | C81: 3/4 D/C SQZ FLEX CONN | D81: 1.99 | F81: =D81*20% -> 0.398 | G81: =F81+D81 -> 2.388 | J81: =SUM(I81*G81) -> 0
B82: 2" U-BOLTS | D82: 3.32 | F82: =D82*20% -> 0.664 | G82: =F82+D82 -> 3.984 | J82: =SUM(I82*G82) -> 0
B83: 3" UNISTRUT CLAMPS | C83: 3" UNISTRUT CLAMPS FOR SMART SENSORS | D83: 4.41 | F83: =D83*20% -> 0.882 | G83: =F83+D83 -> 5.292 | J83: =SUM(I83*G83) -> 0
B84: 2" UNISTRUT CLAMPS | C84: 2" UNISTRUT CLAMPS FOR SENSORS | D84: 3.43 | F84: =D84*20% -> 0.686 | G84: =F84+D84 -> 4.116 | J84: =SUM(I84*G84) -> 0
B85: UNISTRUT PER FOOT | D85: 5.25 | F85: =D85*20% -> 1.05 | G85: =F85+D85 -> 6.3 | J85: =SUM(I85*G85) -> 0
B86: HOASG6X6X4NK | C86: PULL BOX 6X6X4 | D86: 10.93 | F86: =D86*20% -> 2.186 | G86: =F86+D86 -> 13.116 | J86: =SUM(I86*G86) -> 0
B87: PSF6C - CADDY | C87: 6X4.8" ROOFTOP SYS FIXED STRUT SUPPORT | D87: 20.73 | F87: =D87*20% -> 4.146 | G87: =F87+D87 -> 24.876 | J87: =SUM(I87*G87) -> 0
B88: RX21H51 | C88: RAINTIGHT DEV BOX 2 GANG 5 HOLE | D88: 10.72 | F88: =D88*20% -> 2.144 | G88: =F88+D88 -> 12.864 | J88: =SUM(I88*G88) -> 0
B89: AFI CG75K | C89: 3/4IN CORD CONN KIT .125-.880 | D89: 45.31 | F89: =D89*20% -> 9.062 | G89: =F89+D89 -> 54.372 | J89: =SUM(I89*G89) -> 0
B90: MULB 30283 | C90: WP BLANK CVR | D90: 1.49 | F90: =D90*20% -> 0.298 | G90: =F90+D90 -> 1.788 | J90: 0
B91: MULB 30242 | C91: WP ALUM BOX W/LUG | D91: 6.94 | F91: =D91*20% -> 1.388 | G91: =F91+D91 -> 8.328 | J91: =SUM(I91*G91) -> 0
D92: 0 | F92: =D92*20% -> 0 | G92: =F92+D92 -> 0 | J92: =SUM(I92*G92) -> 0
D93: 0 | F93: =D93*20% -> 0 | G93: =F93+D93 -> 0 | J93: =SUM(I93*G93) -> 0
B94: CONTINGENCY | C94: CONTINGENCY | D94: 0 | F94: =D94*20% -> 0 | G94: =F94+D94 -> 0 | I94: 1 | J94: 500
B95: DISPENSER WIRE
B96: PART # | C96: DESCRIPTION | D96: CURRENT PRICE | I96: Amount | J96: Sell Price
F97: =D97*20% -> 0 | G97: =F97+D97 -> 0 | J97: =SUM(I97*G97) -> 0
B98: CUTHN 12G WIRE - BLACK | C98: 12 GAUGE STRANDED WIRE - BLACK 500 FT | D98: 64.81 | F98: =D98*20% -> 12.962 | G98: =F98+D98 -> 77.772 | H98: 0.1 | I98: 5 | J98: =SUM(G98+H98)*I98 -> 389.36
B99: CUTHN 12G WIRE - GREEN | C99: 12 GUAGE STRANDED WIRE - GREEN 500 FT | D99: 64.81 | F99: =D99*20% -> 12.962 | G99: =F99+D99 -> 77.772 | H99: 0.2 | I99: 5 | J99: =SUM(G99+H99)*I99 -> 389.86
B100: CUTHN 12G WIRE - WHITE | C100: 12 GUAGE STRANDED WIRE - WHITE 500 FT | D100: 64.81 | F100: =D100*20% -> 12.962 | G100: =F100+D100 -> 77.772 | H100: 0.2 | I100: 5 | J100: =SUM(G100+H100)*I100 -> 389.86
D101: 0 | F101: =D101*20% -> 0 | G101: =F101+D101 -> 0 | H101: 0.2 | I101: 0 | J101: =SUM(G101+H101)*I101 -> 0
D102: 0 | F102: =D102*20% -> 0 | G102: =F102+D102 -> 0 | J102: =SUM(G102+H102)*I102 -> 0
...

Sheet Source List
A3: 7 ELEVEN # 20412 | B3: Haymarket, VA
A5: SCOPE OF WORK | B5: DESCRIPTION OF WORK:
A6: OPW FLEXWORKS PRODUCT LINES AND 10+1 SHEAR VALVES | B6: REMOVE AND REPLACE EXISTING PRODUCT LINES WITH OPW FLEXORKS DW PIPING USING 7-11 SPEC DPC COUPLINGS AND INSTALL OPW 10+1 SHEAR VALVES
A7: ENTRY FITTINGS | B7: REMOVE AND REPLACE EXISTING UDC AND STP ENTRY FITTINGS WITH BRAVO/ICON SEI SPEC ENTRY BOOTS. HYDRO TEST ALL WORK PRIOR TO START UP FOR VERIFICATION.
A8: TANKNOLOGY / MISC | B8: PURGE, CALIBRATE, START UP DISPENSERS. MEET TANKNOLOGY ONSITE TO ENSURE SMOOTH TRANSITION TO OPEN FUEL SALES.
A9: ** ALL PARTS NUMBERS ARE SUGGESTIONS AND SHOULD ALWAYS DEFAULT TO SEI SPECS
A10: OPW | B10: DESCRIPTION | C10: Units
A11: C15A-250 | B11: 1-1/2" Double Wall Primary Pipe. | C11: 2
A12: DPC-2150A | B12: 1-1/2" Double Wall "Swage" swivel coupling | C12: 24
A13: SEF-1515 | B13: 1-1/2" Elbow NPT Flexworks | C13: 4
A14: STF-1515 | B14: 1-1/2" Junction Tee Fitting - Flexworks | C14: 8
A15: TCT-2509 | B15: Test Jumper For Double Wall Coupling (Dpc Series) 9 inch | C15: 8
A16: TTT-2536 | B16: Test Tube Termination Kit For Double Wall Coupling(Dpc Series) | C16: 4
A17: SMA-1520 | B17: Male Adapter Fittings - Motor Adapter (STP) - 1-1/2"M x 2"M Flex works | C17: 4
A18: OPW-10P-0152 | B18: 10+1-1/2 Inch Double Poppet Emergency Shear Valve | C18: 12
A19: 21BV-0200 | B19: 2" Ball Valve | C19: 4
A20: NOV
A21: 50210101 | B21: PSX-20 AMERON GLUE KITS | C21: 3
A22: 2" Smith NPT | B22: 2" BELL X CAP | C22: 6
A23: Gilbarco
A24: M00703B002 | B24: U-BOLT ENCORE
A25: ICON ENTRY FITTINGS
A26: RECEIVED AT RPS

Sheet Total Receipts
A1: TOTAL RECEIPTS FOR PROJECT
