Workbook
Name EQUIPMENT: EQUIP!$A$1:$A$11
Name PARTS: 'RPS PARTS'!$A$2:$A$1368
Name PARTSCOST: 'RPS PARTS'!$A$2:$B$1368
Name RPSPARTS: PARTS!$A$2:$C$1368

Sheet HEADER LABOR AND MATERIAL
B3: CUSTOMER | C3: SEI COMPLIANCE | D3: Removed liquid from sump. Installed New Nipple, Ball Valve. Cut Line back and installed new opw Swedge fitting on product line.Made connections. Assist Tanknology with line test. Verified passing results.
B4: SITE # | C4: 38980
B5: ADDRESS | C5: 6100 Pouncey Tract Road
B6: CITY, STATE | C6: Glen Allen, VA 23059
B7: INVOICE DATE: | C7: 44788
B8: INVOICE NUMBER:
B9: PROJECT MANAGER
B10: SR#
B11: ELECTRICAL
B12: PART # | C12: DESCRIPTION | D12: CURRENT PRICING | H12: Freight | I12: Amount | J12: Sell Price
B13: 3/4 INCH GALV AND EXPLOSION PROOF
B14: BBDX1 | C14: 1LB DUCK SEAL | D14: 4.53 | F14: 4.53 | G14: 4.53 | J14: 0
B15: CBCHICOA19PX | C15: SEAL COMP | D15: 34.89 | F15: =D15*25% -> 8.7225 | G15: =F15+D15 -> 43.6125 | J15: =SUM(I15*G15) -> 0
B16: CBCHICOA3 | C16: 1LB SEAL COMP - CHICO | D16: 10.48 | F16: =D16*25% -> 2.62 | G16: =F16+D16 -> 13.1 | J16: =SUM(I16*G16) -> 0
B17: CBEYS21 | C17: 3/4 FEM COND SEAL - SEAL OFF | D17: 34.64 | F17: =D17*25% -> 8.66 | G17: =F17+D17 -> 43.3 | J17: =SUM(I17*G17) -> 0
B18: CBGUP214 | C18: GUP214 JCT BOX - LARGE J-BOX | D18: 94.73 | F18: =D18*25% -> 23.6825 | G18: =F18+D18 -> 118.4125 | J18: =SUM(I18*G18) -> 0
B19: CBLBY25 | C19: 3/4 90D COND ELL - PULL 90 | D19: 26 | F19: =D19*25% -> 6.5 | G19: =F19+D19 -> 32.5 | J19: =SUM(I19*G19) -> 0
B20: CBOELB2 | C20: 3/4 OELB COND BODY&CVR L-BOX | D20: 62.22 | F20: =D20*25% -> 15.555 | G20: =F20+D20 -> 77.775 | J20: =SUM(I20*G20) -> 0
B21: CBPLG1 | C21: 1/2 RECES PLUG | D21: 2.9 | F21: =D21*25% -> 0.725 | G21: =F21+D21 -> 3.625 | J21: =SUM(I21*G21) -> 0
B22: CBPLG2 | C22: 3/4 RECES PLUG | D22: 2.35 | F22: =D22*25% -> 0.5875 | G22: =F22+D22 -> 2.9375 | J22: =SUM(I22*G22) -> 0
B23: CBRE21 | C23: 3/4X1/2 REDUCER BUSHING | D23: 0.536 | F23: =D23*25% -> 0.134 | G23: =F23+D23 -> 0.67 | J23: =SUM(I23*G23) -> 0
B24: CBRE32 | C24: 1X3/4 RED | D24: 2.35 | F24: =D24*25% -> 0.5875 | G24: =F24+D24 -> 2.9375 | J24: =SUM(I24*G24) -> 0
B25: CBUNF205 | C25: 3/4 FEM UNION | D25: 26.07 | F25: =D25*25% -> 6.5175 | G25: =F25+D25 -> 32.5875 | J25: =SUM(I25*G25) -> 0
B26: CBUNY205 | C26: 3/4 MALE UNION | D26: 28.5 | F26: =D26*25% -> 7.125 | G26: =F26+D26 -> 35.625 | J26: =SUM(I26*G26) -> 0
... B50: 3/4 INCH ALUMINUM FLEXIBLE COND | C50: FLEXIBLE CONDUIT - 3/4" ALUM -PER FT | D50: 0.9 | F50: =D50*25% -> 0.225 | G50: =F50+D50 -> 1.125 | J50: =SUM(I50*G50) -> 0
B51: EMT 3/4 AND 1 INCH | J51: =SUM(I51*G51) -> 0
B52: 10 FOOT STICK 1" EMT | C52: EMT CONDUIT 10 FOOT - 1 INCH | D52: 14.2 | F52: =D52*25% -> 3.55 | G52: =F52+D52 -> 17.75 | J52: =SUM(I52*G52) -> 0
B53: 10 FOOT STICK 3/4" EMT | C53: 3/4 INCH 10FT STEEL EMT | D53: 8.2 | F53: =D53*25% -> 2.05 | G53: =F53+D53 -> 10.25 | J53: =SUM(I53*G53) -> 0
B54: 3/4" BOX CONNECTOR-COMPRESSION | C54: 3/4 EMT COMPRESSION J BOX CONNECTOR | D54: 1.31 | F54: =D54*25% -> 0.3275 | G54: =F54+D54 -> 1.6375 | J54: =SUM(I54*G54) -> 0
B55: 3/4" COMPRESSION COUPLING | C55: 3/4 EMT COMPRESSION COUPLING | D55: 1.5 | F55: =D55*25% -> 0.375 | G55: =F55+D55 -> 1.875 | J55: =SUM(I55*G55) -> 0
B56: 3/4" COMP COUPLING - RAIN TIGHT | C56: 3/4" RAIN TIGHT COMPRESSION COUPLING | D56: 1.35 | F56: =D56*25% -> 0.3375 | G56: =F56+D56 -> 1.6875 | J56: =SUM(I56*G56) -> 0
B57: EMT PULL 90 3/4" | C57: EMT PULL 90 - 3/4 - RAINT TIGHT | D57: 10.73 | F57: =D57*25% -> 2.6825 | G57: =F57+D57 -> 13.4125 | J57: =SUM(I57*G57) -> 0
B58: EMT 3/4 STRAP | C58: 3/4" STRAP | D58: 0.35 | F58: =D58*25% -> 0.0875 | G58: =F58+D58 -> 0.4375 | J58: =SUM(I58*G58) -> 0
B59: ORBOF7712 | C59: EMT STEEL SET SCREW COUPLING | D59: 0.21 | F59: =D59*25% -> 0.0525 | G59: =F59+D59 -> 0.2625 | J59: =SUM(I59*G59) -> 0
B60: SC500SC | C60: 1/4" BEAM CLAMP 20TPI | D60: 0.81 | F60: =D60*25% -> 0.2025 | G60: =F60+D60 -> 1.0125 | J60: =SUM(I60*G60) -> 0
B61: CF3/4EMTEL | C61: 3/4" EMT ELBOW 90DEG | D61: 2 | F61: =D61*25% -> 0.5 | G61: =F61+D61 -> 2.5 | J61: =SUM(I61*G61) -> 0
B62: SCBU502 | C62: 3/4" 105D PLASTIC BUSHING | D62: 0.1 | F62: =D62*25% -> 0.025 | G62: =F62+D62 -> 0.125 | J62: =SUM(I62*G62) -> 0
B63: 3/4" EMT SWEEP 90 | C63: 3/4" SWEEP 90 | D63: 4.57 | F63: =D63*25% -> 1.1425 | G63: =F63+D63 -> 5.7125 | J63: =SUM(I63*G63) -> 0
B64: 3PC UNION/DB/EP | C64: EXPLOSION PROOF ERICKSON | D64: 33.15 | F64: =D64*25% -> 8.2875 | G64: =F64+D64 -> 41.4375 | J64: =SUM(I64*G64) -> 0
D65: 0 | F65: 0 | G65: 0 | J65: 0
D66: 0 | F66: 0 | G66: 0 | J66: =SUM(I66*G66) -> 0
D67: 0 | F67: 0 | G67: 0 | J67: =SUM(I67*G67) -> 0
B68: 1 INCH FLEXIBLE / GALVANIZED AND EXPLOSION PROOF
B69: EYS31 | C69: 1" EXPLOSION PROOF SEAL OFF | D69: 44.66 | F69: =D69*25% -> 11.165 | G69: =F69+D69 -> 55.825 | J69: =SUM(I69*G69) -> 0
B70: UNF305 | C70: 1" STEEL FEMALE CONDUIT UNION | D70: 49.68 | F70: =D70*25% -> 12.42 | G70: =F70+D70 -> 62.1 | J70: =SUM(I70*G70) -> 0
B71: 1" BOX CONNECT-FLEXIBLE | C71: 1" BOX CONNECTORS-FLEXIBLE | D71: 2.01 | F71: =D71*25% -> 0.5025 | G71: =F71+D71 -> 2.5125 | J71: =SUM(I71*G71) -> 0
B72: 1" FLEXIBLE CONDUIT | C72: FLEXIBLE CONDUIT - 1" - 50 FOOT | D72: 92.53 | F72: =D72*25% -> 23.1325 | G72: =F72+D72 -> 115.6625 | J72: =SUM(I72*G72) -> 0
B73: 1"X6" GALV NIPPLE | C73: 1"X6" GALV NIPPLE | D73: 3.47 | F73: =D73*25% -> 0.8675 | G73: =F73+D73 -> 4.3375 | J73: =SUM(I73*G73) -> 0
B74: 1"XCLOSE | C74: 1" X CLOSE GALVANIZED NIPPLE | D74: 2.13 | F74: =D74*25% -> 0.5325 | G74: =F74+D74 -> 2.6625 | J74: =SUM(I74*G74) -> 0
B75: 100GC | C75: 1 " GALV COUPLING | D75: 2.94 | F75: =D75*25% -> 0.735 | G75: =F75+D75 -> 3.675 | J75: =SUM(I75*G75) -> 0
B76: 1"X2" GALV NIPPLE | C76: 1" X 2" GALVANIZED NIPPLE | D76: 2.62 | F76: =D76*25% -> 0.655 | G76: =F76+D76 -> 3.275 | J76: =SUM(I76*G76) -> 0
B77: 1"x3" GALV NIPPLE | C77: 1"x3" GALV NIPPLE | D77: 3.25 | F77: =D77*25% -> 0.8125 | G77: =F77+D77 -> 4.0625 | J77: =SUM(I77*G77) -> 0
B78: 1"x4" GALV NIPPLE | C78: 1"x4" GALV NIPPLE | D78: 4.25 | F78: =D78*25% -> 1.0625 | G78: =F78+D78 -> 5.3125 | J78: =SUM(I78*G78) -> 0
B79: 1" CONDUIT STRAPS | C79: 1" CONDUIT STRAPS | D79: 0.65 | F79: =D79*25% -> 0.1625 | G79: =F79+D79 -> 0.8125 | J79: =SUM(I79*G79) -> 0
B80: COIGA | C80: 1" GALV CONDUIT - 10 FT | D80: 30.82 | F80: =D80*25% -> 7.705 | G80: =F80+D80 -> 38.525 | J80: =SUM(I80*G80) -> 0
D81: 0 | F81: =D81*25% -> 0 | G81: =F81+D81 -> 0 | J81: =SUM(I81*G81) -> 0
B82: SCBU503 | C82: 1" 105DF PLASTIC BUSHING | D82: 0.17 | F82: =D82*40% -> 0.068 | G82: =F82+D82 -> 0.238 | J82: =SUM(I82*G82) -> 0
B83: MISC ELECTRICAL SUPPLIES
B84: PULL STRING | C84: PULL STRING - CAPITAL ELECTRIC - 2200' | D84: 54.64 | F84: =D84*20% -> 10.928 | G84: =F84+D84 -> 65.568 | J84: =SUM(I84*G84) -> 0
B85: BTP | C85: BLK MI 150# TEE | D85: 147.08 | F85: =D85*20% -> 29.416 | G85: =F85+D85 -> 176.496 | J85: =SUM(I85*G85) -> 0
B86: 2" U-BOLTS | D86: 3.32 | F86: =D86*20% -> 0.664 | G86: =F86+D86 -> 3.984 | J86: =SUM(I86*G86) -> 0
B87: 3" UNISTRUT CLAMPS | C87: 3" UNISTRUT CLAMPS FOR SMART SENSORS | D87: 2.16 | F87: =D87*20% -> 0.432 | G87: =F87+D87 -> 2.592 | J87: =SUM(I87*G87) -> 0
B88: 2" UNISTRUT CLAMPS | C88: 2" UNISTRUT CLAMPS FOR SENSORS | D88: 3.43 | F88: =D88*20% -> 0.686 | G88: =F88+D88 -> 4.116 | J88: =SUM(I88*G88) -> 0
B89: UNISTRUT PER FOOT | D89: 5.25 | F89: =D89*20% -> 1.05 | G89: =F89+D89 -> 6.3 | J89: =SUM(I89*G89) -> 0
B90: HOASG6X6X4NK | C90: PULL BOX 6X6X4 | D90: 10.93 | F90: =D90*20% -> 2.186 | G90: =F90+D90 -> 13.116 | J90: =SUM(I90*G90) -> 0
B91: PSF6C - CADDY | C91: 6X4.8" ROOFTOP SYS FIXED STRUT SUPPORT | D91: 20.73 | F91: =D91*20% -> 4.146 | G91: =F91+D91 -> 24.876 | J91: =SUM(I91*G91) -> 0
B92: RX21H51 | C92: RAINTIGHT DEV BOX 2 GANG 5 HOLE | D92: 10.72 | F92: =D92*20% -> 2.144 | G92: =F92+D92 -> 12.864 | J92: =SUM(I92*G92) -> 0
B93: AFI CG75K | C93: 3/4IN CORD CONN KIT .125-.880 | D93: 45.31 | F93: =D93*20% -> 9.062 | G93: =F93+D93 -> 54.372 | J93: =SUM(I93*G93) -> 0
B94: MULB 30283 | C94: WP BLANK CVR | D94: 1.49 | F94: =D94*20% -> 0.298 | G94: =F94+D94 -> 1.788 | J94: 0
B95: MULB 30242 | C95: WP ALUM BOX W/LUG | D95: 6.94 | F95: =D95*20% -> 1.388 | G95: =F95+D95 -> 8.328 | J95: =SUM(I95*G95) -> 0
B96: 240'SW WIRE FISHTAPE | C96: 240' FISHTAPE - CLEAR CONDUIT | D96: 68.42 | F96: =D96*20% -> 13.684 | G96: =F96+D96 -> 82.104 | J96: =SUM(I96*G96) -> 0
B97: brm21750499 | C97: 0.750"x16' | D97: 30.08 | F97: =D97*20% -> 6.016 | G97: =F97+D97 -> 36.096 | J97: =SUM(I97*G97) -> 0
B98: ELECTRICAL RECEIPTS
F99: =D99*20% -> 0 | G99: =F99+D99 -> 0 | J99: 0
D100: 0 | F100: =D100*20% -> 0 | G100: =F100+D100 -> 0 | J100: =SUM(I100*G100) -> 0
D101: 0 | F101: =D101*20% -> 0 | G101: =F101+D101 -> 0 | J101: =SUM(I101*G101) -> 0
D102: 0 | F102: =D102*20% -> 0 | G102: =F102+D102 -> 0 | J102: =SUM(I102*G102) -> 0
D103: 0 | F103: =D103*20% -> 0 | G103: =F103+D103 -> 0 | J103: =SUM(I103*G103) -> 0
D104: 1 | F104: =D104*20% -> 0.2 | G104: =F104+D104 -> 1.2 | J104: =SUM(I104*G104) -> 0
D105: 2 | F105: =D105*20% -> 0.4 | G105: =F105+D105 -> 2.4 | J105: =SUM(I105*G105) -> 0
D106: 3 | F106: =D106*20% -> 0.6 | G106: =F106+D106 -> 3.6 | J106: =SUM(I106*G106) -> 0
D107: 4 | F107: =D107*20% -> 0.8 | G107: =F107+D107 -> 4.8 | J107: =SUM(I107*G107) -> 0
D108: 5 | F108: =D108*20% -> 1 | G108: =F108+D108 -> 6 | J108: =SUM(I108*G108) -> 0
D109: 6 | F109: =D109*20% -> 1.2 | G109: =F109+D109 -> 7.2 | J109: =SUM(I109*G109) -> 0
D110: 7 | F110: =D110*20% -> 1.4 | G110: =F110+D110 -> 8.4 | J110: =SUM(I110*G110) -> 0
D111: 8 | F111: =D111*20% -> 1.6 | G111: =F111+D111 -> 9.6 | J111: =SUM(I111*G111) -> 0
D112: 0 | F112: =D112*20% -> 0 | G112: =F112+D112 -> 0 | J112: =SUM(I112*G112) -> 0
D113: 0 | F113: =D113*20% -> 0 | G113: =SUM(G99:G112) -> 43.2 | J113: =SUM(I113*G113) -> 0
B114: ELECTRICAL SUPPLIES TOTAL: | J114: =SUM(J14:J100) -> 0
B115: WIRE AND CABLE
B116: PART # | C116: DESCRIPTION | D116: CURRENT PRICE
B118: CUTHN 12G WIRE - BLACK | C118: 12 GAUGE STRANDED WIRE - BLACK 500 FT | D118: 64.81 | F118: =D118*40% -> 25.924 | G118: =F118+D118 -> 90.734 | H118: 0.1 | J118: =SUM(G118+H118)*I118 -> 0
B119: CUTHN 12G WIRE - GREEN | C119: 12 GUAGE STRANDED WIRE - GREEN 500 FT | D119: 64.81 | F119: =D119*40% -> 25.924 | G119: =F119+D119 -> 90.734 | H119: 0.2 | J119: =SUM(G119+H119)*I119 -> 0
B120: CUTHN 12G WIRE - WHITE | C120: 12 GUAGE STRANDED WIRE - WHITE 500 FT | D120: 64.81 | F120: =D120*40% -> 25.924 | G120: =F120+D120 -> 90.734 | H120: 0.2 | J120: =SUM(G120+H120)*I120 -> 0
B121: CUTHN 12G WIRE - WHITE | D121: 0 | F121: =D121*40% -> 0 | G121: =F121+D121 -> 0 | H121: 0.2 | J121: =SUM(G121+H121)*I121 -> 0
B122: 44119 | C122: SHEPHARD12G/14G WIRE | D122: 4817.51 | F122: =D122*20% -> 963.502 | G122: =F122+D122 -> 5781.012 | J122: =SUM(G122+H122)*I122 -> 0
B123: DISPENSER WIRE TOTAL | J123: =SUM(J117:J122) -> 0
B124: PART # | C124: DESCRIPTION | D124: CURRENT PRICE
B125: 3601218-1P STR TFFN 600V Pur-Ylw | C125: 7-11 Spec 18g Twisted "DATA WIRE" - per ft | D125: 0.18 | F125: =D125*40% -> 0.072 | G125: =F125+D125 -> 0.252 | H125: 0.1 | J125: =SUM(G125+H125)*I125 -> 0
B126: WCW7931AFEQ | C126: 7-11 Approved CAT6 Belden Equivalent-per ft | D126: 1.5 | F126: =D126*40% -> 0.6 | G126: =F126+D126 -> 2.1 | H126: 0.2 | J126: =I126*G126 -> 0
...

Sheet PARTS
A1: ITEMS | B1: DESCRIPTION | C1: Price Level 1
A2: FIL-300HS-10 | B2: 10 MIC 3/4 FILTER | C2: 9.69
A3: FIL-40510-AD | B3: SUNOCO FILTER BLUE | C3: 13.79
A4: FIL-40510W-AD | B4: PETRO CLEAR FILTER | C4: 12.38
A5: FIL-40530W-AD | B5: DIESEL FILTER 7-11 SPEC | C5: 9.8
A6: FIL-65 | B6: 70065 400HS-30 TII Filter | C6: 14.8
A7: FIL-70032 450MG | B7: 70032 FILTER | C7: 24.94
A8: FIL-70060 | B8: 400HS-10 FILTER | C8: 14.8
A9: FIL-70064 | B9: 300HS-30 TII Filter | C9: 10.62
A10: FIL-800-30 | B10: 30 MIC FILTER | C10: 22.38
A11: FIL-CC400MB-10 | B11: ETHANOL 1" FILTER | C11: 12.15
A12: FIL-PA04270013 | B12: EPSON PRINTER | C12: 870.72
A13: GIL-EN04002G015 | B13: EXXON OVERLAY RIGHT | C13: 24.67
... A1368: VDR-VR-SENSEMOUNTKIT | B1368: VR SENSE MOUNTING KIT | C1368: 31.8

Sheet RPS PARTS
A1: RPSPARTS | B1: PRICE | C1: Remarks
A2: FIL-300HS-10 - 10 MIC 3/4 FILTER | B2: 13.79
A3: FIL-40510-AD - SUNOCO FILTER BLUE | B3: 12.38
A4: FIL-40510W-AD - PETRO CLEAR FILTER | B4: 9.8
A5: FIL-40530W-AD - DIESEL FILTER 7-11 SPEC | B5: 14.8
A6: FIL-65 - 70065 400HS-30 TII Filter | B6: 24.94
A7: FIL-70032 450MG - 70032 FILTER | B7: 14.8
A8: FIL-70060 - 400HS-10 FILTER | B8: 10.62
A9: FIL-70064 - 300HS-30 TII Filter | B9: 22.38
A10: FIL-800-30 - 30 MIC FILTER | B10: 12.15
A11: FIL-CC400MB-10 - ETHANOL 1" FILTER | B11: 870.72
A12: FIL-PA04270013 - EPSON PRINTER | B12: 24.67
A13: GIL-EN04002G015 - EXXON OVERLAY RIGHT | B13: 23.55
... A1367: VDR-S704-80034FD - USB DRIVE PX60 PASSPORT | B1367: 31.8
A1368: VDR-VR-SENSEMOUNTKIT - VR SENSE MOUNTING KIT

Sheet EQUIP
A1: EQUIPMENT | B1: DESCRIPTION | C1: SERVICE RATE
A2: SKID STEER / FORKS | B2: BOBCAT FOR REMOVING DISPENSERS | C2: 725
A3: SKID STEER / EXCAVATION | B3: DEMO SKID STEER | C3: 775
A4: BREAKER ATTACHMENT | B4: BREAKER ATTACHMENT - EXCAVATION | C4: 195
A5: SCISSOR/ROUGH TERRAIN LIFT | B5: LIFT FOR CANOPY CONDUIT WORK | C5: 890
A6: CONCRETE SAW/DIAMOND BLDE | B6: 16" CONCRETE SAW W/BLADE | C6: 90
A7: P185 AIR COMPRESSOR | B7: AIR COMPRESSOR - CONDUIT CLEAR | C7: 250
A8: DROP TUBE EXTRACTOR | B8: DROP TUBE EXTRACTOR TOOL - REINFORCED TRI-POD/COME ALONG | C8: 75
A9: INTRINSIC SAFE VAC TRAILER | B9: WATER TRAILER FOR HYDRO/PUMPOVER | C9: 225
A10: INTRINSIC SAFE HEATER BLWR | B10: CONFINED SPACE BLOWER/HEATER | C10: 175
A11: SITE FENCING | B11: SITE FENCING - BARRICADES | C11: 225
