Workbook
Name EQUIPMENT: EQUIP!$A$1:$A$11
Name PARTS: #REF!
Name PARTSCOST: #REF!
Name RPSPARTS: PARTS!$A$2:$C$1368

Sheet INVOICE
M2: updated 12/16/20
K7: INVOICE #:
K8: INVOICE DATE: | M8: ='HEADER LABOR AND MATERIAL'!C6 -> 44336
K9: PROJECT FORUM: | M9: ='HEADER LABOR AND MATERIAL'!C9 -> 1-4906517332
C13: CUSTOMER: | K13: SITE LOCATION
C14: 7 ELEVEN INC | K14: STORE# | L14: ='HEADER LABOR AND MATERIAL'!C3 -> 28316
C15: PO BOX 711 | K15: ADDRESS | L15: ='HEADER LABOR AND MATERIAL'!C4 -> 49 PATRICK HENRY WAY
C16: DALLAS, TX 75221 | K16: CITY, STATE, ZIP | M16: ='HEADER LABOR AND MATERIAL'!C5 -> Charles Town
C17: CONSTRUCTION MANAGER
D18: ='HEADER LABOR AND MATERIAL'!C8 -> 0
B22: SCOPE OF WORK
C24: ELECTRICAL SUPPLIES AND MATERIALS | J24: COST | K24: UNIT | L24: SHIP | M24: SUBTOTAL | N24: ELECTRICAL
B25: 1 | C25: ELECTRICAL SUPPLIES AND MATERIALS | N25: ='HEADER LABOR AND MATERIAL'!J116 -> 0
B26: 2 | C26: DISPENSER WIRE | N26: ='HEADER LABOR AND MATERIAL'!J124 -> 0
B27: 3 | C27: CABLE/INTERCOM/CAT6/DATA WIRE | N27: ='HEADER LABOR AND MATERIAL'!J134 -> 0
B28: 4
B29: 5
B30: 6
B31: 7
B32: 8
J33: ELECTRICAL TOTAL: | N33: =SUM(N25:O32) -> 0
C34: HARD PIPING - PLUMBING SUPPLIES | J34: COST | K34: UNIT | L34: FREIGHT | M34: SUBTOTAL | N34: PIPING
B35: 1 | C35: HARD PIPING - STP/DISPENSERS/SPILL BUCKETS AND RISERS | N35: ='HEADER LABOR AND MATERIAL'!J173 -> 0
B36: 2
B37: 3
B38: 4
B39: 5
B40: 6
B41: 7
B42: 8
B43: HARD PIPING TOTAL | N43: ='HEADER LABOR AND MATERIAL'!J173 -> 0
C44: RPS PARTS SOLD | J44: COST | L44: UNIT | M44: SUBTOTAL | N44: TOTAL
B45: 1 | C45: ='HEADER LABOR AND MATERIAL'!C390 | J45: ='HEADER LABOR AND MATERIAL'!D390 -> 0 | L45: ='HEADER LABOR AND MATERIAL'!I390 -> 0 | N45: ='HEADER LABOR AND MATERIAL'!J390 -> 0
B46: 2 | C46: ='HEADER LABOR AND MATERIAL'!C391 | J46: ='HEADER LABOR AND MATERIAL'!D391 -> 0 | L46: ='HEADER LABOR AND MATERIAL'!I391 -> 0 | N46: ='HEADER LABOR AND MATERIAL'!J391 -> 0
B47: 3 | C47: ='HEADER LABOR AND MATERIAL'!C392 | J47: ='HEADER LABOR AND MATERIAL'!D392 -> 0 | L47: ='HEADER LABOR AND MATERIAL'!I392 -> 0 | N47: ='HEADER LABOR AND MATERIAL'!J392 -> 0
B48: 4 | C48: ='HEADER LABOR AND MATERIAL'!C393 | J48: ='HEADER LABOR AND MATERIAL'!D393 -> 0 | L48: ='HEADER LABOR AND MATERIAL'!I393 -> 0 | N48: ='HEADER LABOR AND MATERIAL'!J393 -> 0
B49: 5 | C49: ='HEADER LABOR AND MATERIAL'!C394 | J49: ='HEADER LABOR AND MATERIAL'!D394 -> 0 | L49: ='HEADER LABOR AND MATERIAL'!I394 -> 0 | N49: ='HEADER LABOR AND MATERIAL'!J394 -> 0
B50: 6 | C50: ='HEADER LABOR AND MATERIAL'!C395 | J50: ='HEADER LABOR AND MATERIAL'!D395 -> 0 | L50: ='HEADER LABOR AND MATERIAL'!I395 -> 0 | N50: ='HEADER LABOR AND MATERIAL'!J395 -> 0
B51: 7 | C51: ='HEADER LABOR AND MATERIAL'!C396 | J51: ='HEADER LABOR AND MATERIAL'!D396 -> 0 | L51: ='HEADER LABOR AND MATERIAL'!I396 -> 0 | N51: ='HEADER LABOR AND MATERIAL'!J396 -> 0
B52: 8 | C52: ='HEADER LABOR AND MATERIAL'!C397 | J52: ='HEADER LABOR AND MATERIAL'!D397 -> 0 | L52: ='HEADER LABOR AND MATERIAL'!I397 -> 0 | N52: ='HEADER LABOR AND MATERIAL'!J397 -> 0
B53: 9 | C53: ='HEADER LABOR AND MATERIAL'!C398 | J53: ='HEADER LABOR AND MATERIAL'!D398 -> 0 | L53: ='HEADER LABOR AND MATERIAL'!I398 -> 0 | N53: ='HEADER LABOR AND MATERIAL'!J398 -> 0
B54: 10 | C54: ='HEADER LABOR AND MATERIAL'!#REF! -> #REF! | J54: ='HEADER LABOR AND MATERIAL'!#REF! -> #REF! | L54: ='HEADER LABOR AND MATERIAL'!#REF! -> #REF! | N54: ='HEADER LABOR AND MATERIAL'!#REF! -> #REF!
B55: 11 | C55: ='HEADER LABOR AND MATERIAL'!#REF! -> #REF! | J55: ='HEADER LABOR AND MATERIAL'!#REF! -> #REF! | L55: ='HEADER LABOR AND MATERIAL'!#REF! -> #REF! | N55: ='HEADER LABOR AND MATERIAL'!#REF! -> #REF!
B56: 12 | C56: ='HEADER LABOR AND MATERIAL'!#REF! -> #REF! | J56: ='HEADER LABOR AND MATERIAL'!#REF! -> #REF! | L56: ='HEADER LABOR AND MATERIAL'!#REF! -> #REF! | N56: ='HEADER LABOR AND MATERIAL'!#REF! -> #REF!
B57: 9 | C57: ='HEADER LABOR AND MATERIAL'!#REF! -> #REF! | J57: ='HEADER LABOR AND MATERIAL'!#REF! -> #REF! | L57: ='HEADER LABOR AND MATERIAL'!#REF! -> #REF! | N57: ='HEADER LABOR AND MATERIAL'!#REF! -> #REF!
B58: 10 | C58: ='HEADER LABOR AND MATERIAL'!#REF! -> #REF! | J58: ='HEADER LABOR AND MATERIAL'!#REF! -> #REF! | L58: ='HEADER LABOR AND MATERIAL'!#REF! -> #REF! | N58: ='HEADER LABOR AND MATERIAL'!#REF! -> #REF!
B59: 11 | C59: ='HEADER LABOR AND MATERIAL'!#REF! -> #REF! | J59: ='HEADER LABOR AND MATERIAL'!#REF! -> #REF! | L59: ='HEADER LABOR AND MATERIAL'!#REF! -> #REF! | N59: ='HEADER LABOR AND MATERIAL'!#REF! -> #REF!
B60: 12 | C60: ='HEADER LABOR AND MATERIAL'!#REF! -> #REF! | J60: ='HEADER LABOR AND MATERIAL'!#REF! -> #REF! | L60: ='HEADER LABOR AND MATERIAL'!#REF! -> #REF! | N60: ='HEADER LABOR AND MATERIAL'!#REF! -> #REF!
B61: 13 | C61: ='HEADER LABOR AND MATERIAL'!#REF! -> #REF! | J61: ='HEADER LABOR AND MATERIAL'!#REF! -> #REF! | L61: ='HEADER LABOR AND MATERIAL'!#REF! -> #REF! | N61: ='HEADER LABOR AND MATERIAL'!#REF! -> #REF!
B62: 14 | C62: ='HEADER LABOR AND MATERIAL'!#REF! -> #REF! | L62: ='HEADER LABOR AND MATERIAL'!#REF! -> #REF! | N62: ='HEADER LABOR AND MATERIAL'!#REF! -> #REF!
B63: 15 | C63: ='HEADER LABOR AND MATERIAL'!#REF! -> #REF! | L63: ='HEADER LABOR AND MATERIAL'!#REF! -> #REF!
B64: RPS PARTS INVENTORY SOLD: | N64: ='HEADER LABOR AND MATERIAL'!J399 -> 0
C65: SOURCE / PETRO SUPPLY - PARTS | J65: COST | L65: UNIT | M65: SUBTOTAL | N65: SOURCE/PETRO
B66: 1 | C66: SPILL BUCKETS, MARKERS, HARDWARE, INTERSTITAL TOPS, FIBERGLASS FITTINGS, GLUE, CAPS, ETC | N66: ='HEADER LABOR AND MATERIAL'!J289 -> 0
B67: 2
B68: 3
B69: 4
B70: 6
A71: 6 | B71: 7
B72: 8
B73: 9
B74: SOURCE / PETRO TOTAL: | N74: ='HEADER LABOR AND MATERIAL'!J289 -> 0
C75: RPS MISC RECEIPTS, DISPOSABLES, ETC. | J75: DATE | K75: VENDOR | L75: AMOUNT | M75: UNIT | N75: TOTAL MISC
B76: 1 | C76: GENERAL RECEIPTS/ACETONE/RAGS/PAINT & SUPPLIES/MASKS/CONCRETE SET BOLLARDS/- SEE BREAKDOWN NEXT SHEET | N76: ='HEADER LABOR AND MATERIAL'!J387 -> 230.1
B77: 2
B78: 3
B79: 4
B80: 5
B81: 6
G82: TOTAL MISC RECEIPTS AND DISPOSABLES: | N82: ='HEADER LABOR AND MATERIAL'!J387 -> 230.1
B83: TOTAL PARTS AND MATERIALS - TAXABLE: | N83: =SUM(N74,N82,N64,N43,N33) -> 230.1
C84: EQUIPMENT USE AND RENTAL FEE | J84: COST | K84: HOURS | M84: UNIT | N84: EQUIP TOTAL
B85: 1 | J85: ='HEADER LABOR AND MATERIAL'!D364 -> 0 | M85: 1 | N85: =SUM(M85*J85) -> 0
B86: 2 | J86: ='HEADER LABOR AND MATERIAL'!D365 -> 0 | M86: 1 | N86: =SUM(M86*J86) -> 0
B87: 3 | J87: ='HEADER LABOR AND MATERIAL'!D366 -> 0 | M87: 1 | N87: =SUM(M87*J87) -> 0
B88: 4 | J88: ='HEADER LABOR AND MATERIAL'!D367 -> 0 | M88: 1 | N88: =SUM(M88*J88) -> 0
B89: 5 | N89: =SUM(M89*J89) -> 0
B90: 6 | N90: =SUM(M90*J90) -> 0
B91: 7 | N91: =SUM(M91*J91) -> 0
B92: RPS EQUIPMENT TOTAL: | N92: =SUM(N85:O91) -> 0
C93: RENTAL FEE - RECEIPTS
B94: 1 | C94: ='HEADER LABOR AND MATERIAL'!C372 -> 0 | J94: ='HEADER LABOR AND MATERIAL'!J372 -> 0 | N94: =J94 -> 0
B95: 2 | C95: ='HEADER LABOR AND MATERIAL'!C373 -> 0 | J95: ='HEADER LABOR AND MATERIAL'!J373 -> 0 | N95: =J95 -> 0
B96: 3 | C96: ='HEADER LABOR AND MATERIAL'!C374 -> 0 | J96: ='HEADER LABOR AND MATERIAL'!J374 -> 0 | N96: =J96 -> 0
B97: 4 | C97: ='HEADER LABOR AND MATERIAL'!#REF! -> #REF! | J97: ='HEADER LABOR AND MATERIAL'!#REF! -> #REF! | N97: =J97 -> #REF!
B98: 5 | C98: ='HEADER LABOR AND MATERIAL'!#REF! -> #REF! | J98: ='HEADER LABOR AND MATERIAL'!#REF! -> #REF! | N98: =J98 -> #REF!
B99: 5 | C99: ='HEADER LABOR AND MATERIAL'!#REF! -> #REF! | J99: 880 | N99: =J99 -> 880
B100: TOTAL EQUIPMENT AND RENTAL FEES | N100: ='HEADER LABOR AND MATERIAL'!J375 -> 0
C101: ONSITE LABOR - PER UNIT PRICING | J101: UNITS | K101: QUOTED | L101: HOURS | M101: RATE | N101: TOTAL LABOR
B102: 1 | M102: 70 | N102: =SUM(L102*M102) -> 0
B103: 2 | M103: 70 | N103: =SUM(L103*M103) -> 0
B104: 3 | M104: 70 | N104: =SUM(L104*M104) -> 0
B105: 4 | M105: 70 | N105: =SUM(J105*K105) -> 0
B106: 5 | M106: 70 | N106: =SUM(J106*K106) -> 0
B107: 6 | M107: 70 | N107: =SUM(L107*M107) -> 0
B108: 7 | N108: =SUM(K108*L108) -> 0
J109: TOTAL ONSITE LABOR | N109: ='HEADER LABOR AND MATERIAL'!J335 -> 1400
C110: MOBILIZATION - TRIP CHARGES - TRAVEL | J110: UNITS | K110: QUOTED RATE | L110: HOURS | M110: LABOR RATE | N110: MOBILIZATION
B111: 1 | N111: 0
B112: 2
...

Sheet HEADER LABOR AND MATERIAL
D1: SCOPE OF WORK
B2: CUSTOMER | C2: VIXXO
B3: SITE # | C3: 28316
B4: ADDRESS | C4: =IFERROR(VLOOKUP(C3,SITE!A1:B721,2,FALSE)," ") -> 49 PATRICK HENRY WAY
B5: CITY | C5: =IFERROR(VLOOKUP(C3,SITE!A1:C721,3,FALSE)," ") -> Charles Town
B6: INVOICE DATE: | C6: 44336
B7: INVOICE NUMBER:
B8: PROJECT MANAGER
B9: SR# | C9: 1-4906517332
B10: ELECTRICAL
B11: PART # | C11: DESCRIPTION | D11: CURRENT PRICING | H11: Freight | I11: Amount | J11: Sell Price
B12: 3/4 INCH GALV AND EXPLOSION PROOF
B13: BBDX1 | C13: 1LB DUCK SEAL | D13: 4.53 | F13: =D13*25% -> 1.1325 | G13: =F13+D13 -> 5.6625 | J13: =SUM(I13*G13) -> 0
B14: CBCHICOA19PX | C14: SEAL COMP | D14: 34.89 | F14: =D14*25% -> 8.7225 | G14: =F14+D14 -> 43.6125 | J14: =SUM(I14*G14) -> 0
B15: CBCHICOA3 | C15: 1LB SEAL COMP - CHICO | D15: 10.48 | F15: =D15*25% -> 2.62 | G15: =F15+D15 -> 13.1 | J15: =SUM(I15*G15) -> 0
B16: CBEYS21 | C16: 3/4 FEM COND SEAL - SEAL OFF | D16: 34.64 | F16: =D16*25% -> 8.66 | G16: =F16+D16 -> 43.3 | J16: =SUM(I16*G16) -> 0
B17: CBGUP214 | C17: GUP214 JCT BOX - LARGE J-BOX | D17: 94.73 | F17: =D17*25% -> 23.6825 | G17: =F17+D17 -> 118.4125 | J17: =SUM(I17*G17) -> 0
B18: CBLBY25 | C18: 3/4 90D COND ELL - PULL 90 | D18: 26 | F18: =D18*25% -> 6.5 | G18: =F18+D18 -> 32.5 | J18: =SUM(I18*G18) -> 0
B19: CBOELB2 | C19: 3/4 OELB COND BODY&CVR L-BOX | D19: 62.22 | F19: =D19*25% -> 15.555 | G19: =F19+D19 -> 77.775 | J19: =SUM(I19*G19) -> 0
B20: CBPLG2 | C20: 3/4 RECES PLUG | D20: 2.35 | F20: =D20*25% -> 0.5875 | G20: =F20+D20 -> 2.9375 | J20: =SUM(I20*G20) -> 0
B21: CBRE21 | C21: 3/4X1/2 REDUCER BUSHING | D21: 0.536 | F21: =D21*25% -> 0.134 | G21: =F21+D21 -> 0.67 | J21: =SUM(I21*G21) -> 0
B22: CBRE32 | C22: 1X3/4 RED | D22: 2.35 | F22: =D22*25% -> 0.5875 | G22: =F22+D22 -> 2.9375 | J22: =SUM(I22*G22) -> 0
B23: CBUNF205 | C23: 3/4 FEM UNION | D23: 26.07 | F23: =D23*25% -> 6.5175 | G23: =F23+D23 -> 32.5875 | J23: =SUM(I23*G23) -> 0
B24: CBUNY205 | C24: 3/4 MALE UNION | D24: 28.5 | F24: =D24*25% -> 7.125 | G24: =F24+D24 -> 35.625 | J24: =SUM(I24*G24) -> 0
... B32: CF3/4X10GANIP | C32: 3/4X10 GALV COND NIPPLE | D32: 5.51 | F32: =D32*25% -> 1.3775 | G32: =F32+D32 -> 6.8875 | J32: =SUM(I32*G32) -> 0
B33: CF3/4X12GANIP | C33: 3/4X12 GALV COND NIPPLE | D33: 4.32 | F33: =D33*25% -> 1.08 | G33: =F33+D33 -> 5.4 | I33: 0 | J33: =SUM(I33*G33) -> 0
B34: CF3/4GACP | C34: 3/4" GALV COUPL | D34: 2.147 | F34: =D34*25% -> 0.53675 | G34: =F34+D34 -> 2.68375 | J34: =SUM(I34*G34) -> 0
B35: CO3/4GA | C35: 3/4" GALVANIZED CONDUIT | D35: 13.36 | F35: =D35*25% -> 3.34 | G35: =F35+D35 -> 16.7 | J35: =SUM(I35*G35) -> 0
B36: PV3/4 | C36: 3/4" PVC CONDUIT SCH 40 | D36: 21.93 | F36: =D36*25% -> 5.4825 | G36: =F36+D36 -> 27.4125 | J36: =SUM(I36*G36) -> 0
B37: ID30071 | C37: SIZE 71B GRY WIRECONN | D37: 6.53 | F37: =D37*25% -> 1.6325 | G37: =F37+D37 -> 8.1625 | J37: =SUM(I37*G37) -> 0
B38: ID30072 | C38: SIZE 72B BLU WIRECONN | D38: 7.37 | F38: =D38*25% -> 1.8425 | G38: =F38+D38 -> 9.2125 | J38: =SUM(I38*G38) -> 0
B39: ID30073 | C39: SIZE 73B ORG WIRECONN | D39: 8.52 | F39: =D39*25% -> 2.13 | G39: =F39+D39 -> 10.65 | J39: =SUM(I39*G39) -> 0
B40: PV3/4 | C40: 3/4" PVC CONDUIT SCH 40 | D40: 21.93 | F40: =D40*25% -> 5.4825 | G40: =F40+D40 -> 27.4125 | J40: =SUM(I40*G40) -> 0
B41: PV3/4FTA | C41: 3/4" PVC FEMALE ADAPTER | D41: 0.23 | F41: =D41*25% -> 0.0575 | G41: =F41+D41 -> 0.2875 | J41: =SUM(I41*G41) -> 0
B42: THREADED CONDUIT BUSHING 3/4" | C42: THREADED CONDUIT BUSHING - 3/4 | D42: 0.55 | F42: =D42*25% -> 0.1375 | G42: =F42+D42 -> 0.6875 | J42: =SUM(I42*G42) -> 0
B43: RIGID SWEEP 90 | C43: RIGID SWEEP 90 | D43: 5.91 | F43: =D43*25% -> 1.4775 | G43: =F43+D43 -> 7.3875 | J43: =SUM(I43*G43) -> 0
B44: PVC COATED CONDUIT | C44: ROB ROY | D44: 54 | F44: =D44*25% -> 13.5 | G44: =F44+D44 -> 67.5 | J44: =SUM(I44*G44) -> 0
B45: 3/4" FLEXIBLE CONNECTOR ELBOW | C45: 3/4 FLEX CONDUIT CONNECTOR ELBOW 90 | D45: 1.39 | F45: =D45*25% -> 0.3475 | G45: =F45+D45 -> 1.7375 | J45: =SUM(I45*G45) -> 0
B46: 3/4 INCH ALUMINUM FLEXIBLE COND | C46: FLEXIBLE CONDUIT - 3/4" ALUM -PER FT | D46: 0.9 | F46: =D46*25% -> 0.225 | G46: =F46+D46 -> 1.125 | J46: =SUM(I46*G46) -> 0
B47: EMT 3/4 AND 1 INCH
B48: 10 FOOT STICK 1" EMT | C48: EMT CONDUIT 10 FOOT - 1 INCH | D48: 14.2 | F48: =D48*25% -> 3.55 | G48: =F48+D48 -> 17.75 | J48: =SUM(I48*G48) -> 0
B49: 10 FOOT STICK 3/4" EMT | C49: 3/4 INCH 10FT STEEL EMT | D49: 8.2 | F49: =D49*25% -> 2.05 | G49: =F49+D49 -> 10.25 | J49: =SUM(I49*G49) -> 0
B50: 3/4" BOX CONNECTOR-COMPRESSION | C50: 3/4 EMT COMPRESSION J BOX CONNECTOR | D50: 1.31 | F50: =D50*25% -> 0.3275 | G50: =F50+D50 -> 1.6375 | J50: =SUM(I50*G50) -> 0
B51: 3/4" COMPRESSION COUPLING | C51: 3/4 EMT COMPRESSION COUPLING | D51: 1.5 | F51: =D51*25% -> 0.375 | G51: =F51+D51 -> 1.875 | J51: =SUM(I51*G51) -> 0
B52: 3/4" COMP COUPLING - RAIN TIGHT | C52: 3/4" RAIN TIGHT COMPRESSION COUPLING | D52: 1.35 | F52: =D52*25% -> 0.3375 | G52: =F52+D52 -> 1.6875 | J52: =SUM(I52*G52) -> 0
B53: EMT PULL 90 3/4" | C53: EMT PULL 90 - 3/4 - RAINT TIGHT | D53: 10.73 | F53: =D53*25% -> 2.6825 | G53: =F53+D53 -> 13.4125 | J53: =SUM(I53*G53) -> 0
B54: EMT 3/4 STRAP | C54: 3/4" STRAP | D54: 0.35 | F54: =D54*25% -> 0.0875 | G54: =F54+D54 -> 0.4375 | J54: =SUM(I54*G54) -> 0
B55: ORBOF7712 | C55: EMT STEEL SET SCREW COUPLING | D55: 0.21 | F55: =D55*25% -> 0.0525 | G55: =F55+D55 -> 0.2625 | J55: =SUM(I55*G55) -> 0
B56: SC500SC | C56: 1/4" BEAM CLAMP 20TPI | D56: 0.81 | F56: =D56*25% -> 0.2025 | G56: =F56+D56 -> 1.0125 | J56: =SUM(I56*G56) -> 0
B57: CF3/4EMTEL | C57: 3/4" EMT ELBOW 90DEG | D57: 2 | F57: =D57*25% -> 0.5 | G57: =F57+D57 -> 2.5 | J57: =SUM(I57*G57) -> 0
B58: SCBU502 | C58: 3/4" 105D PLASTIC BUSHING | D58: 0.1 | F58: =D58*25% -> 0.025 | G58: =F58+D58 -> 0.125 | J58: =SUM(I58*G58) -> 0
B59: 3/4" EMT SWEEP 90 | C59: 3/4" SWEEP 90 | D59: 4.57 | F59: =D59*25% -> 1.1425 | G59: =F59+D59 -> 5.7125 | J59: =SUM(I59*G59) -> 0
B60: 3PC UNION/DB/EP | C60: EXPLOSION PROOF ERICKSON | D60: 33.15 | F60: =D60*25% -> 8.2875 | G60: =F60+D60 -> 41.4375 | J60: =SUM(I60*G60) -> 0
B61: 54061312 | C61: 3/4" Rigid Conduit Locknut | D61: 0.43 | F61: =D61*25% -> 0.1075 | G61: =F61+D61 -> 0.5375 | I61: 0 | J61: =SUM(I61*G61) -> 0
D62: 0 | F62: =D62*25% -> 0 | G62: =F62+D62 -> 0 | J62: =SUM(I62*G62) -> 0
D63: 0 | F63: =D63*25% -> 0 | G63: =F63+D63 -> 0 | J63: =SUM(I63*G63) -> 0
B64: 1 INCH FLEXIBLE / GALVANIZED AND EXPLOSION PROOF
B65: EYS31 | C65: 1" EXPLOSION PROOF SEAL OFF | D65: 44.66 | F65: =D65*25% -> 11.165 | G65: =F65+D65 -> 55.825 | J65: =SUM(I65*G65) -> 0
B66: UNF305 | C66: 1" STEEL FEMALE CONDUIT UNION | D66: 49.68 | F66: =D66*25% -> 12.42 | G66: =F66+D66 -> 62.1 | J66: =SUM(I66*G66) -> 0
B67: 1" BOX CONNECT-FLEXIBLE | C67: 1" BOX CONNECTORS-FLEXIBLE | D67: 2.01 | F67: =D67*25% -> 0.5025 | G67: =F67+D67 -> 2.5125 | J67: =SUM(I67*G67) -> 0
B68: 1" FLEXIBLE CONDUIT | C68: FLEXIBLE CONDUIT - 1" - 50 FOOT | D68: 92.53 | F68: =D68*25% -> 23.1325 | G68: =F68+D68 -> 115.6625 | J68: =SUM(I68*G68) -> 0
B69: 1"X6" GALV NIPPLE | C69: 1"X6" GALV NIPPLE | D69: 3.47 | F69: =D69*25% -> 0.8675 | G69: =F69+D69 -> 4.3375 | J69: =SUM(I69*G69) -> 0
B70: 1"XCLOSE | C70: 1" X CLOSE GALVANIZED NIPPLE | D70: 2.13 | F70: =D70*25% -> 0.5325 | G70: =F70+D70 -> 2.6625 | J70: =SUM(I70*G70) -> 0
B71: 100GC | C71: 1 " GALV COUPLING | D71: 2.94 | F71: =D71*25% -> 0.735 | G71: =F71+D71 -> 3.675 | J71: =SUM(I71*G71) -> 0
B72: 1"X2" GALV NIPPLE | C72: 1" X 2" GALVANIZED NIPPLE | D72: 2.62 | F72: =D72*25% -> 0.655 | G72: =F72+D72 -> 3.275 | J72: =SUM(I72*G72) -> 0
B73: 1"x3" GALV NIPPLE | C73: 1"x3" GALV NIPPLE | D73: 3.25 | F73: =D73*25% -> 0.8125 | G73: =F73+D73 -> 4.0625 | J73: =SUM(I73*G73) -> 0
B74: 1"x4" GALV NIPPLE | C74: 1"x4" GALV NIPPLE | D74: 4.25 | F74: =D74*25% -> 1.0625 | G74: =F74+D74 -> 5.3125 | J74: =SUM(I74*G74) -> 0
B75: 1" CONDUIT STRAPS | C75: 1" CONDUIT STRAPS | D75: 0.65 | F75: =D75*25% -> 0.1625 | G75: =F75+D75 -> 0.8125 | J75: =SUM(I75*G75) -> 0
B76: COIGA | C76: 1" GALV CONDUIT - 10 FT | D76: 30.82 | F76: =D76*25% -> 7.705 | G76: =F76+D76 -> 38.525 | J76: =SUM(I76*G76) -> 0
D77: 0 | F77: =D77*25% -> 0 | G77: =F77+D77 -> 0 | J77: =SUM(I77*G77) -> 0
B78: SCBU503 | C78: 1" 105DF PLASTIC BUSHING | D78: 0.17 | F78: =D78*40% -> 0.068 | G78: =F78+D78 -> 0.238 | J78: =SUM(I78*G78) -> 0
B79: MISC ELECTRICAL SUPPLIES
B80: PULL STRING | C80: PULL STRING - CAPITAL ELECTRIC - 2200' | D80: 54.64 | F80: =D80*20% -> 10.928 | G80: =F80+D80 -> 65.568 | J80: =SUM(I80*G80) -> 0
B81: SCXC272 | C81: 3/4 D/C SQZ FLEX CONN | D81: 1.99 | F81: =D81*20% -> 0.398 | G81: =F81+D81 -> 2.388 | J81: =SUM(I81*G81) -> 0
B82: 2" U-BOLTS | D82: 3.32 | F82: =D82*20% -> 0.664 | G82: =F82+D82 -> 3.984 | J82: =SUM(I82*G82) -> 0
B83: 3" UNISTRUT CLAMPS | C83: 3" UNISTRUT CLAMPS FOR SMART SENSORS | D83: 2.16 | F83: =D83*20% -> 0.432 | G83: =F83+D83 -> 2.592 | J83: =SUM(I83*G83) -> 0
B84: 2" UNISTRUT CLAMPS | C84: 2" UNISTRUT CLAMPS FOR SENSORS | D84: 3.43 | F84: =D84*20% -> 0.686 | G84: =F84+D84 -> 4.116 | J84: =SUM(I84*G84) -> 0
B85: UNISTRUT PER FOOT | D85: 5.25 | F85: =D85*20% -> 1.05 | G85: =F85+D85 -> 6.3 | J85: =SUM(I85*G85) -> 0
B86: HOASG6X6X4NK | C86: PULL BOX 6X6X4 | D86: 10.93 | F86: =D86*20% -> 2.186 | G86: =F86+D86 -> 13.116 | J86: =SUM(I86*G86) -> 0
B87: PSF6C - CADDY | C87: 6X4.8" ROOFTOP SYS FIXED STRUT SUPPORT | D87: 20.73 | F87: =D87*20% -> 4.146 | G87: =F87+D87 -> 24.876 | J87: =SUM(I87*G87) -> 0
B88: RX21H51 | C88: RAINTIGHT DEV BOX 2 GANG 5 HOLE | D88: 10.72 | F88: =D88*20% -> 2.144 | G88: =F88+D88 -> 12.864 | J88: =SUM(I88*G88) -> 0
B89: AFI CG75K | C89: 3/4IN CORD CONN KIT .125-.880 | D89: 45.31 | F89: =D89*20% -> 9.062 | G89: =F89+D89 -> 54.372 | J89: =SUM(I89*G89) -> 0
B90: MULB 30283 | C90: WP BLANK CVR | D90: 1.49 | F90: =D90*20% -> 0.298 | G90: =F90+D90 -> 1.788 | J90: 0
B91: MULB 30242 | C91: WP ALUM BOX W/LUG | D91: 6.94 | F91: =D91*20% -> 1.388 | G91: =F91+D91 -> 8.328 | J91: =SUM(I91*G91) -> 0
B92: 240'SW WIRE FISHTAPE | C92: 240' FISHTAPE - CLEAR CONDUIT | D92: 68.42 | F92: =D92*20% -> 13.684 | G92: =F92+D92 -> 82.104 | J92: =SUM(I92*G92) -> 0
B93: CBPLG1 | C93: 1/2 RECES PLUG | D93: 2.82 | F93: =D93*20% -> 0.564 | G93: =F93+D93 -> 3.384 | J93: =SUM(I93*G93) -> 0
B94: ELECTRICAL RECEIPTS
D95: 0 | F95: =D95*20% -> 0 | G95: =F95+D95 -> 0 | I95: 0 | J95: =SUM(I95*G95) -> 0
D96: 0 | F96: =D96*20% -> 0 | G96: =F96+D96 -> 0 | J96: =SUM(I96*G96) -> 0
D97: 0 | F97: =D97*20% -> 0 | G97: =F97+D97 -> 0 | J97: =SUM(I97*G97) -> 0
D98: 0 | F98: =D98*20% -> 0 | G98: =F98+D98 -> 0 | J98: =SUM(I98*G98) -> 0
D99: 0 | F99: =D99*20% -> 0 | G99: =F99+D99 -> 0 | J99: =SUM(I99*G99) -> 0
D100: 0 | F100: =D100*20% -> 0 | G100: =F100+D100 -> 0 | J100: =SUM(I100*G100) -> 0
D101: 0 | F101: =D101*20% -> 0 | G101: =F101+D101 -> 0 | J101: =SUM(I101*G101) -> 0
D102: 0 | F102: =D102*20% -> 0 | G102: =F102+D102 -> 0 | J102: =SUM(I102*G102) -> 0
D103: 0 | F103: =D103*20% -> 0 | G103: =F103+D103 -> 0 | J103: =SUM(I103*G103) -> 0
D104: 0 | F104: =D104*20% -> 0 | G104: =F104+D104 -> 0 | J104: =SUM(I104*G104) -> 0
D105: 0 | F105: =D105*20% -> 0 | G105: =F105+D105 -> 0 | J105: =SUM(I105*G105) -> 0
D106: 0 | F106: =D106*20% -> 0 | G106: =F106+D106 -> 0 | J106: =SUM(I106*G106) -> 0
D107: 0 | F107: =D107*20% -> 0 | G107: =F107+D107 -> 0 | J107: =SUM(I107*G107) -> 0
...

Sheet Wire and Cable
A1: CUTHN 12G WIRE - BLACK | B1: 12 GAUGE STRANDED WIRE - BLACK 500 FT | C1: 64.81
A2: CUTHN 12G WIRE - GREEN | B2: 12 GUAGE STRANDED WIRE - GREEN 500 FT | C2: 64.81
A3: CUTHN 12G WIRE - WHITE | B3: 12 GUAGE STRANDED WIRE - WHITE 500 FT | C3: 64.81
A4: CUTHN 12G WIRE - WHITE | C4: 0
A5: 44119 | B5: SHEPHARD12G/14G WIRE | C5: 4817.51
A6: 3601218-1P STR TFFN 600V Pur-Ylw | B6: 7-11 Spec 18g Twisted "DATA WIRE" - per ft | C6: 0.18
A7: WCW7931AFEQ | B7: 7-11 Approved CAT6 Belden Equivalent-per ft | C7: 1.5
A8: X-779132-001 | B8: BELDEN 7931A -1 7-11 REQ UNTIL 4/1/20 | C8: 2.812
A9: WCW88760FEQ | B9: VEEDER ROOT WIRE - BELDEN 88760 EQ | C9: 0.59
A10: X-873280-001 | B10: 9402 BELDEN EQUAL | C10: 1996
A11: X-806609-001 DATA WIRE 12-14 TPF | B11: TEAS6S-RD-100 - Red / White - ROLL 1000' | C11: 545
A12: X-806609-002 DATA WIRE 12-14 TPF | B12: TEAS6S-BL-100 - Black / White -ROLL 1000' | C12: 545
A13: X-832902-016 4 COND INTERCOM | B13: 4 CONDUCTOR BELDEN 9402 EQ INTERCOM | C13: 1009

Sheet PUMP AND TANK
A1: 1C-3112D | B1: OPW DW Edge Bucket with Drain (Fill) | C1: 817.46
A2: 1C-3112P | B2: OPW DW Edge Bucket with Plug (Vapor) | C2: 817.46
A3: 202135-KIT | B3: OPW DW EDGE PRIMARY LINER KIT, DRAIN | C3: 584.86
A4: 202136-KIT | B4: OPW DW EDGE PRIMARY LINER KIT, PLUG | C4: 584.86
A5: 61SALP-1020-EVR | B5: 4" BRASS SWIVEL ADAPTER - FILL | C5: 212.69
A6: 61VSA-1020-EVR | B6: 4" BRASS VAPOR ADAPTER | C6: 295.85
A7: 634TT-7085-EVR | B7: 4" FILL CAP | C7: 35.5
A8: 1DK-2100-EVR | B8: DRAIN KIT | C8: 65.15
A9: 1711-7085-RVT | B9: 3" ORANGE VAPOR CAP | C9: 34.29
A10: 106N-1100 | B10: #1 Identification Marker(Manufactured by OPW Fueling Components) - Supplier Part Number 106N-1100 | C10: 38
A11: 106N-2200 | B11: #2 Identification Marker(Manufactured by OPW Fueling Components) - Supplier Part Number 106N-2200 | C11: 38
A12: 106U-0125 | B12: Unleaded Identification Marker(Manufactured by OPW Fueling Components) - Supplier Part Number 106U-0125 | C12: 38
... A16: 1TAG-3000 | B16: Identification Tag Premium For Spill Bucket Lid(Manufactured by OPW Fueling Components) - Supplier Part Number 1TAG-3000 | C16: 13.12
C17: 0
A18: 206121 | B18: FSA - EDGE BUCKET ADAPTER - SHORT | C18: 83.36
A19: 206122 | B19: FSA - EDGE BUCKET ADAPTER - TALL | C19: 110.57
A20: FSA-400S | B20: FACE SEAL ADAPTER - SHORT | C20: 65.31
A21: FSA-400 | B21: FACE SEAL ADAPTER - LONG | C21: 65.31
A22: 104A-1800WT | B22: 18" MANHOLE - WATERTIGHT | C22: 209.78
A23: 104A-1200 | B23: 12" ID CAST IRON MANHOLE | C23: 109.29
A24: 104A-1800 | B24: 18' MANHOLE | C24: 153.66
C25: 0
A26: OPW FLEXWORKS
A27: DPC-2150A | B27: 1.5" DW COUPLING (SWAGE FITTING) | C27: 108.67
A28: SBC-2150 | B28: 1.5" DW SWIVEL BOLT ON COUPLING | C28: 172.63
A29: TTT-2536 | B29: TEST TUBE TERMINATION KIT - FLEXWORKS | C29: 27.14
A30: SMA-1520 | B30: 2" X 1.5" MOTOR ADAPTER | C30: 0
C31: 0
C32: 0
C33: 0
A34: OPW
A35: 10P-0152 | B35: 1.5" 10 PLUS DP SHEAR VALVE | C35: 200.91
A36: 71SO-410C | B36: DROP TUBE W/OVERFILL VALVE 10 FOOT | C36: 736.5
A37: 61JSK-44CB | B37: JACK SCREW KIT IRON BASE | C37: 61.69
A38: 71SO-400C | B38: DROP TUBE W/OVERFILL VALVE 8 FOOT | C38: 625.74
A39: UNIVERSAL
C40: 0
A41: 303-1515 | B41: 1.5" Offset - 1.5" | C41: 38.74
A42: 303-1520 | B42: 1.5" Offset - 2" | C42: 38.74
A43: 303-1525 | B43: 1.5" Offset - 2.5" | C43: 44.08
A44: 303-1530 | B44: 1.5" Offset - 3" | C44: 44.08
C45: 0
C46: 0
C47: 0
A48: NOV FIBERGLASS
A49: 22850707 | B49: AM 2" PRIMARY SLEEVE COUPLING | C49: 11.63
A50: 22884386 | B50: AM 2" PRIMARY PIPE PER FOOT | C50: 4.25
A51: 013030-191-4 | B51: SM 2" PRIMARY ADAPT BELL X MALE NPT | C51: 23.8
A52: 012020-180-4 | B52: 2" END CAP | C52: 52.28
A53: 33375001 | B53: 3" PRIMARY END CAP | C53: 62.48
A54: 50210101 | B54: PSX20 ADHESIVE KIT - 5OZ SINGLE | C54: 19.2
A55: 33884381 | B55: AM 3" FRP PIPE - PER FOOT | C55: 6.23
A56: 22372108 | B56: AM 2" PRI 90 DEG ELBOW | C56: 38.1
A57: BRAVO
A58: RF-07-01-U | B58: BRAVO CONDUIT ENTRY FITTING - SPLIT | C58: 131.4
A59: RF-100 EPOXY KIT | B59: BRAVO 7OZ EPOXY KIT | C59: 25.52
C60: 0
A61: CU-380 | B61: ENCORE UNIVERSAL CONVERSION FRAM | C61: 677.35
C62: 0
C63: 0
A64: FIBERLITE
A65: FL42BLACK | B65: 42" FIBERLITE COVER ONLY - OLD STYLE | C65: 1179.11
C66: 0
A67: APT
A68: DCT-400-F | B68: Flexible Ducting Connector | C68: 37.4
A69: Chase Pipe | B69: Flexible Product Line Ducting Per FT | C69: 6.43
C70: 0
A71: ZJI INDUSTRIAL | B71: RF Eco Entry Fitting for Flat surface 3.5" | C71: 271.85
A72: VEEDER ROOT
A73: VDR-0514100-304 | B73: SEAL PACK | C73: 6.46
A74: VDR-33102001 | B74: 1/2" NPT CORD GRIP - SENSOR | C74: 16.2
A75: Sensor Kit | B75: FG Sensor Guide Kit | C75: 92.73

Sheet ICON
A1: ISR 2.0X2.0A | B1: SPLIT REDUCER | C1: 39.6
A2: IAC IBOND50FS | B2: BONDING AGENT FAST SET | C2: 66.28
A3: IRI 3.5xplug | B3: PLUG | C3: 59.2
A4: IRI 2.4x2.0 | B4: Reducing boot | C4: 35.2
A5: IRF 4 B1.4 | B5: 4 Bolt split repair conduit boot | C5: 140
A6: IRF 4B1.0 | B6: 4 Bolt Slit Conduit Repair Boot small | C6: 140
A7: IRF 8B3.5 | B7: 8Bolt Split Flange Repair Boot | C7: 189.6
A8: IRF 8B2.5OS | B8: 8 Bolt Repair Boot - off set | C8: 189.6
A9: IRF 8B2.5 | B9: 8 bolt repair boot | C9: 189.6
A10: IRF 4B1.4NG | B10: 4 Bolt Angled Conduit Entry Boot | C10: 140
A11: IRF 8B2.0 | B11: 8 BOLT REPAIR BOOT | C11: 213.3
A12: ISR 2.5x2.5A | B12: Split Test Boot | C12: 35.2
... A35: IAC PS200 | B35: PETRO SEAL FASKET SEALANT | C35: 80.1

Sheet ELECTRICAL
A1: BBDX1 | B1: 1LB DUCK SEAL | C1: 4.53
A2: CBCHICOA19PX | B2: SEAL COMP | C2: 34.89
A3: CBCHICOA3 | B3: 1LB SEAL COMP - CHICO | C3: 10.48
A4: CBEYS21 | B4: 3/4 FEM COND SEAL - SEAL OFF | C4: 34.64
A5: CBGUP214 | B5: GUP214 JCT BOX - LARGE J-BOX | C5: 94.73
A6: CBLBY25 | B6: 3/4 90D COND ELL - PULL 90 | C6: 26
A7: CBOELB2 | B7: 3/4 OELB COND BODY&CVR L-BOX | C7: 62.22
A8: CBPLG2 | B8: 3/4 RECES PLUG | C8: 2.35
A9: CBRE21 | B9: 3/4X1/2 REDUCER BUSHING | C9: 0.536
A10: CBRE32 | B10: 1X3/4 RED | C10: 2.35
A11: CBUNF205 | B11: 3/4 FEM UNION | C11: 26.07
A12: CBUNY205 | B12: 3/4 MALE UNION | C12: 28.5
... A34: 3/4 INCH ALUMINUM FLEXIBLE COND | B34: FLEXIBLE CONDUIT - 3/4" ALUM -PER FT | C34: 0.9
A35: EMT 3/4 AND 1 INCH
A36: 10 FOOT STICK 1" EMT | B36: EMT CONDUIT 10 FOOT - 1 INCH | C36: 14.2
A37: 10 FOOT STICK 3/4" EMT | B37: 3/4 INCH 10FT STEEL EMT | C37: 8.2
A38: 3/4" BOX CONNECTOR-COMPRESSION | B38: 3/4 EMT COMPRESSION J BOX CONNECTOR | C38: 1.31
A39: 3/4" COMPRESSION COUPLING | B39: 3/4 EMT COMPRESSION COUPLING | C39: 1.5
A40: 3/4" COMP COUPLING - RAIN TIGHT | B40: 3/4" RAIN TIGHT COMPRESSION COUPLING | C40: 1.35
A41: EMT PULL 90 3/4" | B41: EMT PULL 90 - 3/4 - RAINT TIGHT | C41: 10.73
A42: EMT 3/4 STRAP | B42: 3/4" STRAP | C42: 0.35
A43: ORBOF7712 | B43: EMT STEEL SET SCREW COUPLING | C43: 0.21
A44: SC500SC | B44: 1/4" BEAM CLAMP 20TPI | C44: 0.81
A45: CF3/4EMTEL | B45: 3/4" EMT ELBOW 90DEG | C45: 2
A46: SCBU502 | B46: 3/4" 105D PLASTIC BUSHING | C46: 0.1
A47: 3/4" EMT SWEEP 90 | B47: 3/4" SWEEP 90 | C47: 4.57
A48: 3PC UNION/DB/EP | B48: EXPLOSION PROOF ERICKSON | C48: 33.15
A49: 54061312 | B49: 3/4" Rigid Conduit Locknut | C49: 0.43
C50: 0
C51: 0
A52: 1 INCH FLEXIBLE / GALVANIZED AND EXPLOSION PROOF
A53: EYS31 | B53: 1" EXPLOSION PROOF SEAL OFF | C53: 44.66
A54: UNF305 | B54: 1" STEEL FEMALE CONDUIT UNION | C54: 49.68
A55: 1" BOX CONNECT-FLEXIBLE | B55: 1" BOX CONNECTORS-FLEXIBLE | C55: 2.01
A56: 1" FLEXIBLE CONDUIT | B56: FLEXIBLE CONDUIT - 1" - 50 FOOT | C56: 92.53
A57: 1"X6" GALV NIPPLE | B57: 1"X6" GALV NIPPLE | C57: 3.47
A58: 1"XCLOSE | B58: 1" X CLOSE GALVANIZED NIPPLE | C58: 2.13
A59: 100GC | B59: 1 " GALV COUPLING | C59: 2.94
A60: 1"X2" GALV NIPPLE | B60: 1" X 2" GALVANIZED NIPPLE | C60: 2.62
A61: 1"x3" GALV NIPPLE | B61: 1"x3" GALV NIPPLE | C61: 3.25
A62: 1"x4" GALV NIPPLE | B62: 1"x4" GALV NIPPLE | C62: 4.25
A63: 1" CONDUIT STRAPS | B63: 1" CONDUIT STRAPS | C63: 0.65
A64: COIGA | B64: 1" GALV CONDUIT - 10 FT | C64: 30.82
C65: 0
A66: SCBU503 | B66: 1" 105DF PLASTIC BUSHING | C66: 0.17
A67: MISC ELECTRICAL SUPPLIES
A68: PULL STRING | B68: PULL STRING - CAPITAL ELECTRIC - 2200' | C68: 54.64
A69: SCXC272 | B69: 3/4 D/C SQZ FLEX CONN | C69: 1.99
A70: 2" U-BOLTS | C70: 3.32
A71: 3" UNISTRUT CLAMPS | B71: 3" UNISTRUT CLAMPS FOR SMART SENSORS | C71: 2.16
A72: 2" UNISTRUT CLAMPS | B72: 2" UNISTRUT CLAMPS FOR SENSORS | C72: 3.43
A73: UNISTRUT PER FOOT | C73: 5.25
A74: HOASG6X6X4NK | B74: PULL BOX 6X6X4 | C74: 10.93
A75: PSF6C - CADDY | B75: 6X4.8" ROOFTOP SYS FIXED STRUT SUPPORT | C75: 20.73
A76: RX21H51 | B76: RAINTIGHT DEV BOX 2 GANG 5 HOLE | C76: 10.72
A77: AFI CG75K | B77: 3/4IN CORD CONN KIT .125-.880 | C77: 45.31
A78: MULB 30283 | B78: WP BLANK CVR | C78: 1.49
A79: MULB 30242 | B79: WP ALUM BOX W/LUG | C79: 6.94
A80: 240'SW WIRE FISHTAPE | B80: 240' FISHTAPE - CLEAR CONDUIT | C80: 68.42
A81: CBPLG1 | B81: 1/2 RECES PLUG | C81: 2.82

Sheet FERGUSONS
C1: 0
B2: 1 " BLK ML PLUG | C2: 2.09
A3: 1 1/2 INCH
C4: 0
A5: IBNJCL | B5: 1.5"xCLOSE BLK NIPPLE | C5: 3.58
A6: IBNKM | B6: 1.5"X 3" BLK NIPPLE | C6: 5.6
B7: 1.5" X 4" BLK NIPPLE | C7: 3
B8: 1.5" X 4.5" BLK NIPPLE | C8: 4.5
B9: 1.5" x 5" BLK NIPPLE | C9: 5.89
B10: 1.5" x 5.5" BLK NIPPLE | C10: 6.81
B11: 1.5" X 6" BLK NIPPLE | C11: 7.21
B12: 1.5" X 8" BLK NIPPLE | C12: 0
B13: 1.5" X 10" BLK NIPPLE | C13: 0
B14: 1.5" X 12" BLK NIPPLE | C14: 17.65
C15: 0
C16: 0
A17: 2 INCH
C18: 0
A19: BCK | B19: 2 BLK MI 150# COUP | C19: 11.06
A20: IBNKL | B20: 2X2-1/2 BLK STL NIP | C20: 0
A21: IBNKCL | B21: 2XCLOSE BLK STL NIP | C21: 4.88
A22: IBNKL | B22: 2X2-1/2 BLK STL NIP | C22: 0
A23: IBNKR | B23: 2X4" BLK STL NIPPLE | C23: 6.77
A24: IBBKD | B24: 2X4.5" BLK STL NIPPLE | C24: 7.8
A25: IB4K | B25: 2" 45 ELBOW | C25: 15.14
A26: IB150UK | B26: 2" BLK STL UNION 150# | C26: 30.95
A27: IBTK | B27: 2" BLK STL 150# TEE | C27: 20.52
A28: IB9K | B28: 2" BLK STL 150# 90 ELBOW | C28: 14.26
C29: 0
A30: FERGUSON RECEIPT | B30: 2" GALV ELBOW | C30: 22.81
A31: 4 INCH
A32: IBCP | B32: 4" BLACK STEEL COUPLING 150# | C32: 80.26
A33: IBNP12 | B33: 4" X 12" BLK STL NIPPLE | C33: 59.41
A34: IB150UJ | B34: 4" X 5" BLK STL NIPPLE | C34: 36.06
B35: 4" X CLOSE | C35: 27.29
B36: 4" X 8" BLK STL NIPPLE | C36: 44.5
B37: 4" X 36" BLK STL NIPPLE | C37: 136.24
A38: IBNPP | B38: 4" X 4" | C38: 31.57
B39: 4" X 6" | C39: 30.96

Sheet PARTS
A1: Item ID | B1: Description | C1: Price Level 1
A2: FIL-300HS-10 | B2: 10 MIC 3/4 FILTER | C2: 9.69
A3: FIL-40510-AD | B3: SUNOCO FILTER BLUE | C3: 13.79
A4: FIL-40510W-AD | B4: PETRO CLEAR FILTER | C4: 12.38
A5: FIL-40530W-AD | B5: DIESEL FILTER 7-11 SPEC | C5: 9.8
A6: FIL-65 | B6: 70065 400HS-30 TII Filter | C6: 14.8
A7: FIL-70032 450MG | B7: 70032 FILTER | C7: 24.94
A8: FIL-70060 | B8: 400HS-10 FILTER | C8: 14.8
A9: FIL-70064 | B9: 300HS-30 TII Filter | C9: 10.62
A10: FIL-800-30 | B10: 30 MIC FILTER | C10: 22.38
A11: FIL-CC400MB-10 | B11: ETHANOL 1" FILTER | C11: 12.15
A12: FIL-PA04270013 | B12: EPSON PRINTER | C12: 870.72
A13: GIL-EN04002G015 | B13: EXXON OVERLAY RIGHT | C13: 24.67
... A1281: VDR-VR-SENSEMOUNTKIT | B1281: VR SENSE MOUNTING KIT | C1281: 31.8

Sheet EQUIP
A1: EQUIPMENT | B1: DESCRIPTION | C1: SERVICE RATE
A2: SKID STEER / FORKS | B2: BOBCAT FOR REMOVING DISPENSERS | C2: 725
A3: SKID STEER / EXCAVATION | B3: DEMO SKID STEER | C3: 775
A4: BREAKER ATTACHMENT | B4: BREAKER ATTACHMENT - EXCAVATION | C4: 195
A5: SCISSOR/ROUGH TERRAIN LIFT | B5: LIFT FOR CANOPY CONDUIT WORK | C5: 890
A6: CONCRETE SAW/DIAMOND BLDE | B6: 16" CONCRETE SAW W/BLADE | C6: 90
A7: P185 AIR COMPRESSOR | B7: AIR COMPRESSOR - CONDUIT CLEAR | C7: 250
A8: DROP TUBE EXTRACTOR | B8: DROP TUBE EXTRACTOR TOOL - REINFORCED TRI-POD/COME ALONG | C8: 75
A9: INTRINSIC SAFE VAC TRAILER | B9: WATER TRAILER FOR HYDRO/PUMPOVER | C9: 225
A10: INTRINSIC SAFE HEATER BLWR | B10: CONFINED SPACE BLOWER/HEATER | C10: 175
A11: SITE FENCING | B11: SITE FENCING - BARRICADES | C11: 225

Sheet SITE
A1: Store Number | B1: Address | C1: City | D1: State | E1: Zip Code | F1: Phone Number
A2: 10634 | B2: 7800 CENTREVILLE RD | C2: Manassas | D2: VA | E2: 201111954 | F2: (703)368-3753
A3: 10635 | B3: 10911 MAIN ST | C3: Fairfax | D3: VA | E3: 220304703 | F3: (703)359-3559
A4: 10638 | B4: 110 DRYMILL RD | C4: Leesburg | D4: VA | E4: 201752612 | F4: (703)777-6816
A5: 10643 | B5: 10008 MAIN ST | C5: Fairfax | D5: VA | E5: 220313404 | F5: (703)359-3560
A6: 10645 | B6: 537 MAPLE AV | C6: Vienna | D6: VA | E6: 221804226 | F6: (703)255-9301
A7: 10646 | B7: 8211 OLD CENTREVILLE ROAD | C7: Manassas | D7: VA | E7: 201112116 | F7: (703)368-0027
A8: 10647 | B8: 3910 UNIVERSITY DR | C8: Fairfax | D8: VA | E8: 220302507 | F8: (703)359-3561
A9: 10651 | B9: 9908 GEORGETOWN PIKE | C9: Great Falls | D9: VA | E9: 22066 | F9: (703)759-5788
A10: 10652 | B10: 427 MAPLE AVE | C10: Vienna | D10: VA | E10: 221804722 | F10: (703)255-9302
A11: 10653 | B11: 701 VANBUREN ST | C11: Herndon | D11: VA | E11: 201704722 | F11: (571)203-9618
A12: 10654 | B12: 7420 OLD CENTREVILLE ROAD | C12: Manassas | D12: VA | E12: 201111642 | F12: (703)368-7201
A13: 10656 | B13: 712 W CHURCH ST | C13: Sterling | D13: VA | E13: 201644610 | F13: (703)444-1215
... A626: 39977 | B626: 1230 WOLF ROCK DR | C626: Purcellville | D626: VA | E626: 20132 | F626: (000)000-0000
A627: 40000 | B627: 701 Bermuda Hundred Rd | C627: Chester | D627: VA | E627: 23836 | F627: 8045300170
A628: 40001 | B628: 3384 Hwy 903 | C628: Bracey | D628: VA | E628: 23919 | F628: 4346892400
A629: 40002 | B629: 402 Virginia Ave. | C629: Clarksville | D629: VA | E629: 23927 | F629: 4343742003
A630: 40003 | B630: 213 West 2Nd Street | C630: Chase City | D630: VA | E630: 23924 | F630: 4343722437
A631: 40005 | B631: 961 Temple Ave. | C631: Colonial Heights | D631: VA | E631: 23834 | F631: 8045209528
A632: 40006 | B632: 111 S. County Dr. | C632: Wakefield | D632: VA | E632: 23888 | F632: 7578993310
A633: 40007 | B633: 10031 Hull St. Road | C633: North Chesterfield | D633: VA | E633: 23236 | F633: 8046752050
A634: 40009 | B634: 2753 W. Broad St. | C634: Richmond | D634: VA | E634: 23220 | F634: (804) 213-9746
A635: 40011 | B635: 7041 Commons Plza | C635: Chesterfield | D635: VA | E635: 23832 | F635: 8047686310
A636: 40012 | B636: 4810 Forest Hill Ave. | C636: Richmond | D636: VA | E636: 23225 | F636: 8048645490
A637: 40013 | B637: 1701 East Broad St. | C637: Richmond | D637: VA | E637: 23223 | F637: 8048645309
A638: 40014 | B638: 8188 Hwy 15 P.O Box 4 | C638: Clarksville | D638: VA | E638: 23927 | F638: 4343749808
A639: 40016 | B639: 11600 Midlothian Turnpike | C639: Midlothian | D639: VA | E639: 23113 | F639: 8043788700
A640: 40017 | B640: 8601 Patterson Ave. | C640: Richmond | D640: VA | E640: 23229 | F640: 8048645378
A641: 40019 | B641: 15418 Patrick Henry Hwy | C641: Amelia Ch | D641: VA | E641: 23002 | F641: 8045617331
A642: 40020 | B642: 7009 Pole Green Road | C642: Mechanicsville | D642: VA | E642: 23116 | F642: 8045598009
A643: 40021 | B643: 12201 S. Crater Road. | C643: Petersburg | D643: VA | E643: 23805 | F643: 8047331132
A644: 40022 | B644: 9900 Chester Road | C644: Chester | D644: VA | E644: 23831 | F644: 8047688171
A645: 40023 | B645: 2320 W. Hundred Road | C645: Chester | D645: VA | E645: 23831 | F645: 8047175736
A646: 40024 | B646: 2117 Willis Road | C646: Richmond | D646: VA | E646: 23237 | F646: 8042713491
... A650: 40029 | B650: 812 England Street | C650: Ashland | D650: VA | E650: 23005 | F650: 8047984176
A651: 40030 | B651: 14600 Time Square Dr. | C651: Midlothian | D651: VA | E651: 23112 | F651: (804) 739-5942
A652: 40032 | B652: 7020 Staples Mill Road | C652: Richmond | D652: VA | E652: 23228 | F652: 8046580725
A653: 40033 | B653: 3310 Church Road | C653: Richmond | D653: VA | E653: 23233 | F653: 8042705686
A654: 40035 | B654: 1120 East Atlantic Street | C654: La Crosse | D654: VA | E654: 23950 | F654: 4347577845
A655: 40037 | B655: 280 Garrisonville Rd | C655: Stafford | D655: VA | E655: 22554 | F655: 5402889944
A656: 40038 | B656: 15701 Carrs Brooke Way | C656: Manassas | D656: VA | E656: 20112 | F656: 7037635451
A657: 40039 | B657: 3201 Plank Rd | C657: Fredericksburg | D657: VA | E657: 22407 | F657: (540) 786-2927
A658: 40040 | B658: 5123 Mudd Tavern Rd | C658: Woodford | D658: VA | E658: 22580 | F658: 5405825150
A659: 40042 | B659: 7113 SUDLEY RD | C659: Manassas | D659: VA | E659: 20109 | F659: (703)392-3946
A660: 40043 | B660: 8005 Sudley Rd | C660: Manassas | D660: VA | E660: 20109 | F660: (703) 369-1983
A661: 40044 | B661: 5409 Jefferson Davis Hwy | C661: Fredericksburg | D661: VA | E661: 22407 | F661: (540) 898-6714
A662: 40046 | B662: 5135 Westfield Blvd | C662: Centreville | D662: VA | E662: 20120 | F662: (571) 485-9175
A663: 40047 | B663: 43971 Farmwell Hunt Plaza | C663: Ashburn | D663: VA | E663: 20147 | F663: 7038585419
A664: 40048 | B664: 23501 Overland Dr | C664: Sterling | D664: VA | E664: 20166 | F664: 7036610873
A665: 40049 | B665: 9879 Liberia Ave | C665: Manassas | D665: VA | E665: 20110 | F665: (703) 366-3724
A666: 40050 | B666: 22405 Flagstaff Plaza | C666: Ashburn | D666: VA | E666: 20148 | F666: 7038585397
A667: 40053 | B667: 43740 Parkhurst Plaza | C667: Ashburn | D667: VA | E667: 20147 | F667: 7037293411
A668: 40055 | B668: 2990 Centreville Rd | C668: Herndon | D668: VA | E668: 20171 | F668: (703) 435-9104
A669: 40056 | B669: 11854 Sunrise Valley Dr | C669: Reston | D669: VA | E669: 20191 | F669: 7038605996
A670: 40057 | B670: 1818 Wiehle Ave | C670: Reston | D670: VA | E670: 20190 | F670: 7034678270
A671: 40058 | B671: 11519 Leesburg Pike | C671: Herndon | D671: VA | E671: 20170 | F671: 7034213735
A672: 40059 | B672: 13825 Lee Highway | C672: Centreville | D672: VA | E672: 20121 | F672: 7032669530
A673: 40060 | B673: 2601 QUINCY ADAMS RD | C673: Herndon | D673: VA | E673: 20171 | F673: (703)860-8972
A674: 40061 | B674: 11416 York Road | C674: Hunt Valley | D674: MD | E674: 21030 | F674: 4107719662
A675: 40063 | B675: 4625 Cleburne Blvd | C675: Dublin | D675: VA | E675: 24084 | F675: 5406434000
A676: 40065 | B676: 4622 Cleburne Blvd | C676: Dublin | D676: VA | E676: 24084 | F676: 5406434009
A677: 40066 | B677: 44950 Rudder Road | C677: Sterling | D677: VA | E677: 20166 | F677: 7036612164
A678: 40102 | B678: 42870 Truro Parish Drive | C678: Ashburn | D678: VA | E678: 20148 | F678: 7037260201
A679: 40103 | B679: 43270 Defender Drive | C679: South Riding | D679: VA | E679: 20152 | F679: 7033270021
A680: 40104 | B680: 4601 N. Washington Blvd | C680: Arlington | D680: VA | E680: 22201 | F680: 7035280646
A681: 40107 | B681: 7025 Old Keene Mill Rd | C681: Springfield | D681: VA | E681: 22150 | F681: 7036444129
A682: 40109 | B682: 44111 Ashburn Shopping Plaza | C682: Ashburn | D682: VA | E682: 20147 | F682: 7037299833
A683: 40290 | B683: 20850 Hardwood Forest Dr | C683: Sterling | D683: VA | E683: 20165 | F683: 7034217313
A684: 40305 | B684: 13300 Franklin Farm Rd | C684: Herndon | D684: VA | E684: 20171 | F684: 7034710018
A685: 40312 | B685: 4647 West Ox Road | C685: Fairfax | D685: VA | E685: 22030 | F685: 7039880038
... A690: 40390 | B690: 8915 Ox Road | C690: Lorton | D690: VA | E690: 22079 | F690: 7034939577
A691: 40392 | B691: 12730 SHOPPES LANE | C691: Fairfax | D691: VA | E691: 22033 | F691: (703)378-1959
A692: 40398 | B692: 11516 Leesburg Pike | C692: Herndon | D692: VA | E692: 20170 | F692: 7034304578
A693: 40400 | B693: 7320 Gambrill Rd | C693: Springfield | D693: VA | E693: 22153 | F693: 7036442257
A694: 40414 | B694: 13617 Lee Jackson Highway | C694: Chantilly | D694: VA | E694: 20151 | F694: 7033789538
A695: 40419 | B695: 10619 Braddock Rd | C695: Fairfax | D695: VA | E695: 22032 | F695: 7032738636
A696: 40424 | B696: 615 EAST MARKET ST | C696: Leesburg | D696: VA | E696: 20176 | F696: (703)777-8313
A697: 597 | B697: 1401 Hampton Pk Blvd | C697: Capitol Heights | D697: MD | E697: 20742 | F697: (301) 336-1704
A698: 580 | B698: 16410 McKendree Road | C698: Brandywine | D698: MD | F698: (301) 782-7432
A699: 590 | B699: 805 LEIDY RD | C699: Westminster | D699: MD | E699: 21157 | F699: (410) 871-1009
A700: 597 | B700: 1401 Hampton Pk Blvd | C700: Capitol Heights | D700: MD | E700: 20743 | F700: (301) 336-1704
A701: 651 | B701: 14461 Lee Hwy | C701: Gainesville | D701: VA | E701: 20155 | F701: (571) 261-4089
A702: 653 | B702: 4625 Harrison Rd | C702: Fredericksburg | D702: VA | E702: 22408 | F702: (540) 898-3701
A703: 658 | B703: 3402 SHANNON PARK DR | C703: Fredericksburg | D703: va | E703: 22401 | F703: (540) 368-3924
A704: 660 | B704: 1140 Carl D Silver Pkwy | C704: Fredericksburg | D704: VA | E704: 22192 | F704: (540) 785-3438
A705: 661 | B705: 13350 MINNIEVILLE RD | C705: Woodbridge | D705: va | E705: 22192 | F705: (703) 492-9984
A706: 662 | B706: 2051 DANIEL STEWART SQUARE | C706: Woodbridge | D706: VA | E706: 22192 | F706: (703) 492-9858
A707: 663 | B707: 10628 COURTHOUSE RD | C707: Fredericksburg | D707: va | E707: 22407 | F707: (540) 898-4278
A708: 664 | B708: 4527 PLANK RD | C708: Fredericksburg | D708: VA | E708: 22407 | F708: (540) 785-5535
A709: 665 | B709: 72 Austin Pk | C709: Stafford | D709: VA | E709: 22554 | F709: (540) 288-0655
A710: 667 | B710: 2390 Plank Rd | C710: Fredericksburg | D710: VA | E710: 22401 | F710: (540) 899-2043
... A719: 8622 | B719: 531 W. Shirley Ave | C719: Warrenton | D719: VA | E719: 20186 | F719: (540) 349-8999
A720: 8639 | B720: 3450 Historic Sully Way | C720: Chantilly | D720: VA
A721: 8640 | B721: 23055 Oakgrove Rd | C721: Sterling | D721: VA | E721: 20166
